[
  {
    "author": "LMB Studio",
    "link_thumb": "https://live.staticflickr.com/65535/51682796723_12ab5ace72_o.gif",
    "link_bin": "https://github.com/lmbstudiocontact/mb4_59/raw/main/Naruto Anime_L8_693255232.bin",
    "id_bin": "Naruto Anime_L8_693255232",
    "list_language": [
      {
        "author": "LMB Studio",
        "link_thumb": "https://live.staticflickr.com/65535/51682797008_f39ed3e91e_o.gif",
        "link_bin": "https://github.com/lmbstudiocontact/mb4_59/raw/main/Naruto Anime_L8_693255232_English.bin",
        "name_language": "English",
        "id_bin_language": "Naruto Anime_L8_693255232_English"
      },
      {
        "author": "LMB Studio",
        "link_thumb": "https://live.staticflickr.com/65535/51683427655_18ccc096e7_o.gif",
        "link_bin": "https://github.com/lmbstudiocontact/mb4_59/raw/main/Naruto Anime_L8_693255232_Portuguese.bin",
        "name_language": "Portuguese",
        "id_bin_language": "Naruto Anime_L8_693255232_Portuguese"
      },
      {
        "author": "LMB Studio",
        "link_thumb": "https://live.staticflickr.com/65535/51682538321_33eaf112ea_o.gif",
        "link_bin": "https://github.com/lmbstudiocontact/mb4_59/raw/main/Naruto Anime_L8_693255232_Russian.bin",
        "name_language": "Russian",
        "id_bin_language": "Naruto Anime_L8_693255232_Russian"
      },
      {
        "author": "LMB Studio",
        "link_thumb": "https://live.staticflickr.com/65535/51681743197_d6c5feb10c_o.gif",
        "link_bin": "https://github.com/lmbstudiocontact/mb4_59/raw/main/Naruto Anime_L8_693255232_Spanish.bin",
        "name_language": "Spanish",
        "id_bin_language": "Naruto Anime_L8_693255232_Spanish"
      }
    ],
    "array_tags": [
      "lmbstudio"
    ],
    "list_album": [
      {
        "id_album": "1894397990",
        "link_thumb": "https://live.staticflickr.com/65535/51682796723_12ab5ace72_o.gif",
        "title": "Naruto Anime_L8"
      }
    ]
  },
  {
    "author": "LMB Studio",
    "link_thumb": "https://live.staticflickr.com/65535/51682538981_edd0b90349_o.gif",
    "link_bin": "https://github.com/lmbstudiocontact/mb4_59/raw/main/Naruto Anime_L9_-1081277805.bin",
    "id_bin": "Naruto Anime_L9_-1081277805",
    "list_language": [
      {
        "author": "LMB Studio",
        "link_thumb": "https://live.staticflickr.com/65535/51683428770_32fa4e5e12_o.gif",
        "link_bin": "https://github.com/lmbstudiocontact/mb4_59/raw/main/Naruto Anime_L9_-1081277805_English.bin",
        "name_language": "English",
        "id_bin_language": "Naruto Anime_L9_-1081277805_English"
      },
      {
        "author": "LMB Studio",
        "link_thumb": "https://live.staticflickr.com/65535/51683210174_0a3a5f6f57_o.gif",
        "link_bin": "https://github.com/lmbstudiocontact/mb4_59/raw/main/Naruto Anime_L9_-1081277805_Portuguese.bin",
        "name_language": "Portuguese",
        "id_bin_language": "Naruto Anime_L9_-1081277805_Portuguese"
      },
      {
        "author": "LMB Studio",
        "link_thumb": "https://live.staticflickr.com/65535/51681744462_2c68842fd2_o.gif",
        "link_bin": "https://github.com/lmbstudiocontact/mb4_59/raw/main/Naruto Anime_L9_-1081277805_Russian.bin",
        "name_language": "Russian",
        "id_bin_language": "Naruto Anime_L9_-1081277805_Russian"
      },
      {
        "author": "LMB Studio",
        "link_thumb": "https://live.staticflickr.com/65535/51683429665_2e60d0a013_o.gif",
        "link_bin": "https://github.com/lmbstudiocontact/mb4_59/raw/main/Naruto Anime_L9_-1081277805_Spanish.bin",
        "name_language": "Spanish",
        "id_bin_language": "Naruto Anime_L9_-1081277805_Spanish"
      }
    ],
    "array_tags": [
      "lmbstudio"
    ],
    "list_album": [
      {
        "id_album": "1894397991",
        "link_thumb": "https://live.staticflickr.com/65535/51682538981_edd0b90349_o.gif",
        "title": "Naruto Anime_L9"
      }
    ]
  },
  {
    "author": "LMB Studio",
    "link_thumb": "https://live.staticflickr.com/65535/51681744992_b526c78663_o.gif",
    "link_bin": "https://github.com/lmbstudiocontact/mb4_59/raw/main/Naruto Anime_L9_-1081277827.bin",
    "id_bin": "Naruto Anime_L9_-1081277827",
    "list_language": [
      {
        "author": "LMB Studio",
        "link_thumb": "https://live.staticflickr.com/65535/51682540566_6c8e2cf8d4_o.gif",
        "link_bin": "https://github.com/lmbstudiocontact/mb4_59/raw/main/Naruto Anime_L9_-1081277827_English.bin",
        "name_language": "English",
        "id_bin_language": "Naruto Anime_L9_-1081277827_English"
      },
      {
        "author": "LMB Studio",
        "link_thumb": "https://live.staticflickr.com/65535/51681745447_3ac794d99e_o.gif",
        "link_bin": "https://github.com/lmbstudiocontact/mb4_59/raw/main/Naruto Anime_L9_-1081277827_Portuguese.bin",
        "name_language": "Portuguese",
        "id_bin_language": "Naruto Anime_L9_-1081277827_Portuguese"
      },
      {
        "author": "LMB Studio",
        "link_thumb": "https://live.staticflickr.com/65535/51683211579_f495146b4e_o.gif",
        "link_bin": "https://github.com/lmbstudiocontact/mb4_59/raw/main/Naruto Anime_L9_-1081277827_Russian.bin",
        "name_language": "Russian",
        "id_bin_language": "Naruto Anime_L9_-1081277827_Russian"
      },
      {
        "author": "LMB Studio",
        "link_thumb": "https://live.staticflickr.com/65535/51682541281_b851b80e2c_o.gif",
        "link_bin": "https://github.com/lmbstudiocontact/mb4_59/raw/main/Naruto Anime_L9_-1081277827_Spanish.bin",
        "name_language": "Spanish",
        "id_bin_language": "Naruto Anime_L9_-1081277827_Spanish"
      }
    ],
    "array_tags": [
      "lmbstudio"
    ],
    "list_album": [
      {
        "id_album": "1894397991",
        "link_thumb": "https://live.staticflickr.com/65535/51681744992_b526c78663_o.gif",
        "title": "Naruto Anime_L9"
      }
    ]
  },
  {
    "author": "LMB Studio",
    "link_thumb": "https://live.staticflickr.com/65535/51683431170_9f8727548a_o.gif",
    "link_bin": "https://github.com/lmbstudiocontact/mb4_59/raw/main/Naruto Anime_L9_-1405662507.bin",
    "id_bin": "Naruto Anime_L9_-1405662507",
    "list_language": [
      {
        "author": "LMB Studio",
        "link_thumb": "https://live.staticflickr.com/65535/51683431415_8efa5cca61_o.gif",
        "link_bin": "https://github.com/lmbstudiocontact/mb4_59/raw/main/Naruto Anime_L9_-1405662507_English.bin",
        "name_language": "English",
        "id_bin_language": "Naruto Anime_L9_-1405662507_English"
      },
      {
        "author": "LMB Studio",
        "link_thumb": "https://live.staticflickr.com/65535/51682542051_5405b08376_o.gif",
        "link_bin": "https://github.com/lmbstudiocontact/mb4_59/raw/main/Naruto Anime_L9_-1405662507_Portuguese.bin",
        "name_language": "Portuguese",
        "id_bin_language": "Naruto Anime_L9_-1405662507_Portuguese"
      },
      {
        "author": "LMB Studio",
        "link_thumb": "https://live.staticflickr.com/65535/51682542266_02313197d3_o.gif",
        "link_bin": "https://github.com/lmbstudiocontact/mb4_59/raw/main/Naruto Anime_L9_-1405662507_Russian.bin",
        "name_language": "Russian",
        "id_bin_language": "Naruto Anime_L9_-1405662507_Russian"
      },
      {
        "author": "LMB Studio",
        "link_thumb": "https://live.staticflickr.com/65535/51682542521_60497cce4e_o.gif",
        "link_bin": "https://github.com/lmbstudiocontact/mb4_59/raw/main/Naruto Anime_L9_-1405662507_Spanish.bin",
        "name_language": "Spanish",
        "id_bin_language": "Naruto Anime_L9_-1405662507_Spanish"
      }
    ],
    "array_tags": [
      "lmbstudio"
    ],
    "list_album": [
      {
        "id_album": "1894397991",
        "link_thumb": "https://live.staticflickr.com/65535/51683431170_9f8727548a_o.gif",
        "title": "Naruto Anime_L9"
      }
    ]
  },
  {
    "author": "LMB Studio",
    "link_thumb": "https://live.staticflickr.com/65535/51682542791_985535223b_o.gif",
    "link_bin": "https://github.com/lmbstudiocontact/mb4_59/raw/main/Naruto Anime_L9_-1418008956.bin",
    "id_bin": "Naruto Anime_L9_-1418008956",
    "list_language": [
      {
        "author": "LMB Studio",
        "link_thumb": "https://live.staticflickr.com/65535/51682801978_b07f9e3008_o.gif",
        "link_bin": "https://github.com/lmbstudiocontact/mb4_59/raw/main/Naruto Anime_L9_-1418008956_English.bin",
        "name_language": "English",
        "id_bin_language": "Naruto Anime_L9_-1418008956_English"
      },
      {
        "author": "LMB Studio",
        "link_thumb": "https://live.staticflickr.com/65535/51683213869_a088826f36_o.gif",
        "link_bin": "https://github.com/lmbstudiocontact/mb4_59/raw/main/Naruto Anime_L9_-1418008956_Portuguese.bin",
        "name_language": "Portuguese",
        "id_bin_language": "Naruto Anime_L9_-1418008956_Portuguese"
      },
      {
        "author": "LMB Studio",
        "link_thumb": "https://live.staticflickr.com/65535/51683433145_092fe1178d_o.gif",
        "link_bin": "https://github.com/lmbstudiocontact/mb4_59/raw/main/Naruto Anime_L9_-1418008956_Russian.bin",
        "name_language": "Russian",
        "id_bin_language": "Naruto Anime_L9_-1418008956_Russian"
      },
      {
        "author": "LMB Studio",
        "link_thumb": "https://live.staticflickr.com/65535/51683214274_2c57b88d86_o.gif",
        "link_bin": "https://github.com/lmbstudiocontact/mb4_59/raw/main/Naruto Anime_L9_-1418008956_Spanish.bin",
        "name_language": "Spanish",
        "id_bin_language": "Naruto Anime_L9_-1418008956_Spanish"
      }
    ],
    "array_tags": [
      "lmbstudio"
    ],
    "list_album": [
      {
        "id_album": "1894397991",
        "link_thumb": "https://live.staticflickr.com/65535/51682542791_985535223b_o.gif",
        "title": "Naruto Anime_L9"
      }
    ]
  },
  {
    "author": "LMB Studio",
    "link_thumb": "https://live.staticflickr.com/65535/51683433795_ee60333852_o.gif",
    "link_bin": "https://github.com/lmbstudiocontact/mb4_59/raw/main/Naruto Anime_L9_-1418008957.bin",
    "id_bin": "Naruto Anime_L9_-1418008957",
    "list_language": [
      {
        "author": "LMB Studio",
        "link_thumb": "https://live.staticflickr.com/65535/51682544481_3c72df07fa_o.gif",
        "link_bin": "https://github.com/lmbstudiocontact/mb4_59/raw/main/Naruto Anime_L9_-1418008957_English.bin",
        "name_language": "English",
        "id_bin_language": "Naruto Anime_L9_-1418008957_English"
      },
      {
        "author": "LMB Studio",
        "link_thumb": "https://live.staticflickr.com/65535/51683215099_6a087e7edb_o.gif",
        "link_bin": "https://github.com/lmbstudiocontact/mb4_59/raw/main/Naruto Anime_L9_-1418008957_Portuguese.bin",
        "name_language": "Portuguese",
        "id_bin_language": "Naruto Anime_L9_-1418008957_Portuguese"
      },
      {
        "author": "LMB Studio",
        "link_thumb": "https://live.staticflickr.com/65535/51682545001_f65e940fa7_o.gif",
        "link_bin": "https://github.com/lmbstudiocontact/mb4_60/raw/main/Naruto Anime_L9_-1418008957_Russian.bin",
        "name_language": "Russian",
        "id_bin_language": "Naruto Anime_L9_-1418008957_Russian"
      },
      {
        "author": "LMB Studio",
        "link_thumb": "https://live.staticflickr.com/65535/51682545191_149ab43c00_o.gif",
        "link_bin": "https://github.com/lmbstudiocontact/mb4_60/raw/main/Naruto Anime_L9_-1418008957_Spanish.bin",
        "name_language": "Spanish",
        "id_bin_language": "Naruto Anime_L9_-1418008957_Spanish"
      }
    ],
    "array_tags": [
      "lmbstudio"
    ],
    "list_album": [
      {
        "id_album": "1894397991",
        "link_thumb": "https://live.staticflickr.com/65535/51683433795_ee60333852_o.gif",
        "title": "Naruto Anime_L9"
      }
    ]
  },
  {
    "author": "LMB Studio",
    "link_thumb": "https://live.staticflickr.com/65535/51681750047_b05464a070_o.gif",
    "link_bin": "https://github.com/lmbstudiocontact/mb4_60/raw/main/Naruto Anime_L9_-1418008958.bin",
    "id_bin": "Naruto Anime_L9_-1418008958",
    "list_language": [
      {
        "author": "LMB Studio",
        "link_thumb": "https://live.staticflickr.com/65535/51682545741_fc7cdcb5be_o.gif",
        "link_bin": "https://github.com/lmbstudiocontact/mb4_60/raw/main/Naruto Anime_L9_-1418008958_English.bin",
        "name_language": "English",
        "id_bin_language": "Naruto Anime_L9_-1418008958_English"
      },
      {
        "author": "LMB Studio",
        "link_thumb": "https://live.staticflickr.com/65535/51682804713_4da81dde0e_o.gif",
        "link_bin": "https://github.com/lmbstudiocontact/mb4_60/raw/main/Naruto Anime_L9_-1418008958_Portuguese.bin",
        "name_language": "Portuguese",
        "id_bin_language": "Naruto Anime_L9_-1418008958_Portuguese"
      },
      {
        "author": "LMB Studio",
        "link_thumb": "https://live.staticflickr.com/65535/51683216614_e56f9dce27_o.gif",
        "link_bin": "https://github.com/lmbstudiocontact/mb4_60/raw/main/Naruto Anime_L9_-1418008958_Russian.bin",
        "name_language": "Russian",
        "id_bin_language": "Naruto Anime_L9_-1418008958_Russian"
      },
      {
        "author": "LMB Studio",
        "link_thumb": "https://live.staticflickr.com/65535/51682546521_bc478b2d1e_o.gif",
        "link_bin": "https://github.com/lmbstudiocontact/mb4_60/raw/main/Naruto Anime_L9_-1418008958_Spanish.bin",
        "name_language": "Spanish",
        "id_bin_language": "Naruto Anime_L9_-1418008958_Spanish"
      }
    ],
    "array_tags": [
      "lmbstudio"
    ],
    "list_album": [
      {
        "id_album": "1894397991",
        "link_thumb": "https://live.staticflickr.com/65535/51681750047_b05464a070_o.gif",
        "title": "Naruto Anime_L9"
      }
    ]
  },
  {
    "author": "LMB Studio",
    "link_thumb": "https://live.staticflickr.com/65535/51681751317_d4cf6f583e_o.gif",
    "link_bin": "https://github.com/lmbstudiocontact/mb4_60/raw/main/Naruto Anime_L9_-1418008959.bin",
    "id_bin": "Naruto Anime_L9_-1418008959",
    "list_language": [
      {
        "author": "LMB Studio",
        "link_thumb": "https://live.staticflickr.com/65535/51682805763_604ca4fe9a_o.gif",
        "link_bin": "https://github.com/lmbstudiocontact/mb4_60/raw/main/Naruto Anime_L9_-1418008959_English.bin",
        "name_language": "English",
        "id_bin_language": "Naruto Anime_L9_-1418008959_English"
      },
      {
        "author": "LMB Studio",
        "link_thumb": "https://live.staticflickr.com/65535/51681751837_9ea942bfd4_o.gif",
        "link_bin": "https://github.com/lmbstudiocontact/mb4_60/raw/main/Naruto Anime_L9_-1418008959_Portuguese.bin",
        "name_language": "Portuguese",
        "id_bin_language": "Naruto Anime_L9_-1418008959_Portuguese"
      },
      {
        "author": "LMB Studio",
        "link_thumb": "https://live.staticflickr.com/65535/51681752122_4cd3e21a8b_o.gif",
        "link_bin": "https://github.com/lmbstudiocontact/mb4_60/raw/main/Naruto Anime_L9_-1418008959_Russian.bin",
        "name_language": "Russian",
        "id_bin_language": "Naruto Anime_L9_-1418008959_Russian"
      },
      {
        "author": "LMB Studio",
        "link_thumb": "https://live.staticflickr.com/65535/51682547656_d8428e99c2_o.gif",
        "link_bin": "https://github.com/lmbstudiocontact/mb4_60/raw/main/Naruto Anime_L9_-1418008959_Spanish.bin",
        "name_language": "Spanish",
        "id_bin_language": "Naruto Anime_L9_-1418008959_Spanish"
      }
    ],
    "array_tags": [
      "lmbstudio"
    ],
    "list_album": [
      {
        "id_album": "1894397991",
        "link_thumb": "https://live.staticflickr.com/65535/51681751317_d4cf6f583e_o.gif",
        "title": "Naruto Anime_L9"
      }
    ]
  },
  {
    "author": "LMB Studio",
    "link_thumb": "https://live.staticflickr.com/65535/51681752597_a1093b369f_o.gif",
    "link_bin": "https://github.com/lmbstudiocontact/mb4_60/raw/main/Naruto Anime_L9_-1418037667.bin",
    "id_bin": "Naruto Anime_L9_-1418037667",
    "list_language": [
      {
        "author": "LMB Studio",
        "link_thumb": "https://live.staticflickr.com/65535/51683218534_5fe6353892_o.gif",
        "link_bin": "https://github.com/lmbstudiocontact/mb4_60/raw/main/Naruto Anime_L9_-1418037667_English.bin",
        "name_language": "English",
        "id_bin_language": "Naruto Anime_L9_-1418037667_English"
      },
      {
        "author": "LMB Studio",
        "link_thumb": "https://live.staticflickr.com/65535/51681753167_8ccfbd158a_o.gif",
        "link_bin": "https://github.com/lmbstudiocontact/mb4_60/raw/main/Naruto Anime_L9_-1418037667_Portuguese.bin",
        "name_language": "Portuguese",
        "id_bin_language": "Naruto Anime_L9_-1418037667_Portuguese"
      },
      {
        "author": "LMB Studio",
        "link_thumb": "https://live.staticflickr.com/65535/51683219044_542a99f0ce_o.gif",
        "link_bin": "https://github.com/lmbstudiocontact/mb4_60/raw/main/Naruto Anime_L9_-1418037667_Russian.bin",
        "name_language": "Russian",
        "id_bin_language": "Naruto Anime_L9_-1418037667_Russian"
      },
      {
        "author": "LMB Studio",
        "link_thumb": "https://live.staticflickr.com/65535/51683219304_9618c119a6_o.gif",
        "link_bin": "https://github.com/lmbstudiocontact/mb4_60/raw/main/Naruto Anime_L9_-1418037667_Spanish.bin",
        "name_language": "Spanish",
        "id_bin_language": "Naruto Anime_L9_-1418037667_Spanish"
      }
    ],
    "array_tags": [
      "lmbstudio"
    ],
    "list_album": [
      {
        "id_album": "1894397991",
        "link_thumb": "https://live.staticflickr.com/65535/51681752597_a1093b369f_o.gif",
        "title": "Naruto Anime_L9"
      }
    ]
  },
  {
    "author": "LMB Studio",
    "link_thumb": "https://live.staticflickr.com/65535/51682549231_6f465bebb1_o.gif",
    "link_bin": "https://github.com/lmbstudiocontact/mb4_60/raw/main/Naruto Anime_L9_-1418037668.bin",
    "id_bin": "Naruto Anime_L9_-1418037668",
    "list_language": [
      {
        "author": "LMB Studio",
        "link_thumb": "https://live.staticflickr.com/65535/51683438900_0c6b76182e_o.gif",
        "link_bin": "https://github.com/lmbstudiocontact/mb4_60/raw/main/Naruto Anime_L9_-1418037668_English.bin",
        "name_language": "English",
        "id_bin_language": "Naruto Anime_L9_-1418037668_English"
      },
      {
        "author": "LMB Studio",
        "link_thumb": "https://live.staticflickr.com/65535/51682549766_c7b7125d4b_o.gif",
        "link_bin": "https://github.com/lmbstudiocontact/mb4_60/raw/main/Naruto Anime_L9_-1418037668_Portuguese.bin",
        "name_language": "Portuguese",
        "id_bin_language": "Naruto Anime_L9_-1418037668_Portuguese"
      },
      {
        "author": "LMB Studio",
        "link_thumb": "https://live.staticflickr.com/65535/51682550006_d8496cab05_o.gif",
        "link_bin": "https://github.com/lmbstudiocontact/mb4_60/raw/main/Naruto Anime_L9_-1418037668_Russian.bin",
        "name_language": "Russian",
        "id_bin_language": "Naruto Anime_L9_-1418037668_Russian"
      },
      {
        "author": "LMB Studio",
        "link_thumb": "https://live.staticflickr.com/65535/51683220549_22f5544e57_o.gif",
        "link_bin": "https://github.com/lmbstudiocontact/mb4_60/raw/main/Naruto Anime_L9_-1418037668_Spanish.bin",
        "name_language": "Spanish",
        "id_bin_language": "Naruto Anime_L9_-1418037668_Spanish"
      }
    ],
    "array_tags": [
      "lmbstudio"
    ],
    "list_album": [
      {
        "id_album": "1894397991",
        "link_thumb": "https://live.staticflickr.com/65535/51682549231_6f465bebb1_o.gif",
        "title": "Naruto Anime_L9"
      }
    ]
  },
  {
    "author": "LMB Studio",
    "link_thumb": "https://live.staticflickr.com/65535/51683440070_46ec017596_o.gif",
    "link_bin": "https://github.com/lmbstudiocontact/mb4_60/raw/main/Naruto Anime_L9_-1418037879.bin",
    "id_bin": "Naruto Anime_L9_-1418037879",
    "list_language": [
      {
        "author": "LMB Studio",
        "link_thumb": "https://live.staticflickr.com/65535/51681755317_d7ea27dfb9_o.gif",
        "link_bin": "https://github.com/lmbstudiocontact/mb4_60/raw/main/Naruto Anime_L9_-1418037879_English.bin",
        "name_language": "English",
        "id_bin_language": "Naruto Anime_L9_-1418037879_English"
      },
      {
        "author": "LMB Studio",
        "link_thumb": "https://live.staticflickr.com/65535/51682809828_79c42b765c_o.gif",
        "link_bin": "https://github.com/lmbstudiocontact/mb4_60/raw/main/Naruto Anime_L9_-1418037879_Portuguese.bin",
        "name_language": "Portuguese",
        "id_bin_language": "Naruto Anime_L9_-1418037879_Portuguese"
      },
      {
        "author": "LMB Studio",
        "link_thumb": "https://live.staticflickr.com/65535/51682551456_d687c1e1e7_o.gif",
        "link_bin": "https://github.com/lmbstudiocontact/mb4_60/raw/main/Naruto Anime_L9_-1418037879_Russian.bin",
        "name_language": "Russian",
        "id_bin_language": "Naruto Anime_L9_-1418037879_Russian"
      },
      {
        "author": "LMB Studio",
        "link_thumb": "https://live.staticflickr.com/65535/51682810353_4d6a760db5_o.gif",
        "link_bin": "https://github.com/lmbstudiocontact/mb4_60/raw/main/Naruto Anime_L9_-1418037879_Spanish.bin",
        "name_language": "Spanish",
        "id_bin_language": "Naruto Anime_L9_-1418037879_Spanish"
      }
    ],
    "array_tags": [
      "lmbstudio"
    ],
    "list_album": [
      {
        "id_album": "1894397991",
        "link_thumb": "https://live.staticflickr.com/65535/51683440070_46ec017596_o.gif",
        "title": "Naruto Anime_L9"
      }
    ]
  },
  {
    "author": "LMB Studio",
    "link_thumb": "https://live.staticflickr.com/65535/51683221999_3b62164ae2_o.gif",
    "link_bin": "https://github.com/lmbstudiocontact/mb4_60/raw/main/Naruto Anime_L9_-1471850873.bin",
    "id_bin": "Naruto Anime_L9_-1471850873",
    "list_language": [
      {
        "author": "LMB Studio",
        "link_thumb": "https://live.staticflickr.com/65535/51683222239_da9e6df833_o.gif",
        "link_bin": "https://github.com/lmbstudiocontact/mb4_60/raw/main/Naruto Anime_L9_-1471850873_English.bin",
        "name_language": "English",
        "id_bin_language": "Naruto Anime_L9_-1471850873_English"
      },
      {
        "author": "LMB Studio",
        "link_thumb": "https://live.staticflickr.com/65535/51682552421_c4c3bb478b_o.gif",
        "link_bin": "https://github.com/lmbstudiocontact/mb4_60/raw/main/Naruto Anime_L9_-1471850873_Portuguese.bin",
        "name_language": "Portuguese",
        "id_bin_language": "Naruto Anime_L9_-1471850873_Portuguese"
      },
      {
        "author": "LMB Studio",
        "link_thumb": "https://live.staticflickr.com/65535/51682552736_49f31766db_o.gif",
        "link_bin": "https://github.com/lmbstudiocontact/mb4_60/raw/main/Naruto Anime_L9_-1471850873_Russian.bin",
        "name_language": "Russian",
        "id_bin_language": "Naruto Anime_L9_-1471850873_Russian"
      },
      {
        "author": "LMB Studio",
        "link_thumb": "https://live.staticflickr.com/65535/51682552951_b193d348c8_o.gif",
        "link_bin": "https://github.com/lmbstudiocontact/mb4_60/raw/main/Naruto Anime_L9_-1471850873_Spanish.bin",
        "name_language": "Spanish",
        "id_bin_language": "Naruto Anime_L9_-1471850873_Spanish"
      }
    ],
    "array_tags": [
      "lmbstudio"
    ],
    "list_album": [
      {
        "id_album": "1894397991",
        "link_thumb": "https://live.staticflickr.com/65535/51683221999_3b62164ae2_o.gif",
        "title": "Naruto Anime_L9"
      }
    ]
  },
  {
    "author": "LMB Studio",
    "link_thumb": "https://live.staticflickr.com/65535/51683442520_cb5281cc43_o.gif",
    "link_bin": "https://github.com/lmbstudiocontact/mb4_60/raw/main/Naruto Anime_L9_-1619083516.bin",
    "id_bin": "Naruto Anime_L9_-1619083516",
    "list_language": [
      {
        "author": "LMB Studio",
        "link_thumb": "https://live.staticflickr.com/65535/51682553431_68bd07c51f_o.gif",
        "link_bin": "https://github.com/lmbstudiocontact/mb4_60/raw/main/Naruto Anime_L9_-1619083516_English.bin",
        "name_language": "English",
        "id_bin_language": "Naruto Anime_L9_-1619083516_English"
      },
      {
        "author": "LMB Studio",
        "link_thumb": "https://live.staticflickr.com/65535/51683442945_04467972d8_o.gif",
        "link_bin": "https://github.com/lmbstudiocontact/mb4_60/raw/main/Naruto Anime_L9_-1619083516_Portuguese.bin",
        "name_language": "Portuguese",
        "id_bin_language": "Naruto Anime_L9_-1619083516_Portuguese"
      },
      {
        "author": "LMB Studio",
        "link_thumb": "https://live.staticflickr.com/65535/51682553801_f4107f06b0_o.gif",
        "link_bin": "https://github.com/lmbstudiocontact/mb4_60/raw/main/Naruto Anime_L9_-1619083516_Russian.bin",
        "name_language": "Russian",
        "id_bin_language": "Naruto Anime_L9_-1619083516_Russian"
      },
      {
        "author": "LMB Studio",
        "link_thumb": "https://live.staticflickr.com/65535/51683224114_1673d582a3_o.gif",
        "link_bin": "https://github.com/lmbstudiocontact/mb4_60/raw/main/Naruto Anime_L9_-1619083516_Spanish.bin",
        "name_language": "Spanish",
        "id_bin_language": "Naruto Anime_L9_-1619083516_Spanish"
      }
    ],
    "array_tags": [
      "lmbstudio"
    ],
    "list_album": [
      {
        "id_album": "1894397991",
        "link_thumb": "https://live.staticflickr.com/65535/51683442520_cb5281cc43_o.gif",
        "title": "Naruto Anime_L9"
      }
    ]
  },
  {
    "author": "LMB Studio",
    "link_thumb": "https://live.staticflickr.com/65535/51683444025_c56cbca7ac_o.gif",
    "link_bin": "https://github.com/lmbstudiocontact/mb4_60/raw/main/Naruto Anime_L9_-1804760705.bin",
    "id_bin": "Naruto Anime_L9_-1804760705",
    "list_language": [
      {
        "author": "LMB Studio",
        "link_thumb": "https://live.staticflickr.com/65535/51681759062_1301cb32e2_o.gif",
        "link_bin": "https://github.com/lmbstudiocontact/mb4_60/raw/main/Naruto Anime_L9_-1804760705_English.bin",
        "name_language": "English",
        "id_bin_language": "Naruto Anime_L9_-1804760705_English"
      },
      {
        "author": "LMB Studio",
        "link_thumb": "https://live.staticflickr.com/65535/51683225429_2df3c112fd_o.gif",
        "link_bin": "https://github.com/lmbstudiocontact/mb4_60/raw/main/Naruto Anime_L9_-1804760705_Portuguese.bin",
        "name_language": "Portuguese",
        "id_bin_language": "Naruto Anime_L9_-1804760705_Portuguese"
      },
      {
        "author": "LMB Studio",
        "link_thumb": "https://live.staticflickr.com/65535/51683444900_62896e4132_o.gif",
        "link_bin": "https://github.com/lmbstudiocontact/mb4_60/raw/main/Naruto Anime_L9_-1804760705_Russian.bin",
        "name_language": "Russian",
        "id_bin_language": "Naruto Anime_L9_-1804760705_Russian"
      },
      {
        "author": "LMB Studio",
        "link_thumb": "https://live.staticflickr.com/65535/51682555836_37a81b24d6_o.gif",
        "link_bin": "https://github.com/lmbstudiocontact/mb4_60/raw/main/Naruto Anime_L9_-1804760705_Spanish.bin",
        "name_language": "Spanish",
        "id_bin_language": "Naruto Anime_L9_-1804760705_Spanish"
      }
    ],
    "array_tags": [
      "lmbstudio"
    ],
    "list_album": [
      {
        "id_album": "1894397991",
        "link_thumb": "https://live.staticflickr.com/65535/51683444025_c56cbca7ac_o.gif",
        "title": "Naruto Anime_L9"
      }
    ]
  },
  {
    "author": "LMB Studio",
    "link_thumb": "https://live.staticflickr.com/65535/51683226119_96bd8073c4_o.gif",
    "link_bin": "https://github.com/lmbstudiocontact/mb4_60/raw/main/Naruto Anime_L9_-1849312367.bin",
    "id_bin": "Naruto Anime_L9_-1849312367",
    "list_language": [
      {
        "author": "LMB Studio",
        "link_thumb": "https://live.staticflickr.com/65535/51683226339_6729745a4b_o.gif",
        "link_bin": "https://github.com/lmbstudiocontact/mb4_60/raw/main/Naruto Anime_L9_-1849312367_English.bin",
        "name_language": "English",
        "id_bin_language": "Naruto Anime_L9_-1849312367_English"
      },
      {
        "author": "LMB Studio",
        "link_thumb": "https://live.staticflickr.com/65535/51682556746_ef5656da53_o.gif",
        "link_bin": "https://github.com/lmbstudiocontact/mb4_60/raw/main/Naruto Anime_L9_-1849312367_Portuguese.bin",
        "name_language": "Portuguese",
        "id_bin_language": "Naruto Anime_L9_-1849312367_Portuguese"
      },
      {
        "author": "LMB Studio",
        "link_thumb": "https://live.staticflickr.com/65535/51681760932_28bd55385f_o.gif",
        "link_bin": "https://github.com/lmbstudiocontact/mb4_60/raw/main/Naruto Anime_L9_-1849312367_Russian.bin",
        "name_language": "Russian",
        "id_bin_language": "Naruto Anime_L9_-1849312367_Russian"
      },
      {
        "author": "LMB Studio",
        "link_thumb": "https://live.staticflickr.com/65535/51683226999_53671862e5_o.gif",
        "link_bin": "https://github.com/lmbstudiocontact/mb4_60/raw/main/Naruto Anime_L9_-1849312367_Spanish.bin",
        "name_language": "Spanish",
        "id_bin_language": "Naruto Anime_L9_-1849312367_Spanish"
      }
    ],
    "array_tags": [
      "lmbstudio"
    ],
    "list_album": [
      {
        "id_album": "1894397991",
        "link_thumb": "https://live.staticflickr.com/65535/51683226119_96bd8073c4_o.gif",
        "title": "Naruto Anime_L9"
      }
    ]
  },
  {
    "author": "LMB Studio",
    "link_thumb": "https://live.staticflickr.com/65535/51683227214_451d0b735f_o.gif",
    "link_bin": "https://github.com/lmbstudiocontact/mb4_60/raw/main/Naruto Anime_L9_-196727997.bin",
    "id_bin": "Naruto Anime_L9_-196727997",
    "list_language": [
      {
        "author": "LMB Studio",
        "link_thumb": "https://live.staticflickr.com/65535/51681761687_da191d1b06_o.gif",
        "link_bin": "https://github.com/lmbstudiocontact/mb4_60/raw/main/Naruto Anime_L9_-196727997_English.bin",
        "name_language": "English",
        "id_bin_language": "Naruto Anime_L9_-196727997_English"
      },
      {
        "author": "LMB Studio",
        "link_thumb": "https://live.staticflickr.com/65535/51681761992_b2481a6920_o.gif",
        "link_bin": "https://github.com/lmbstudiocontact/mb4_60/raw/main/Naruto Anime_L9_-196727997_Portuguese.bin",
        "name_language": "Portuguese",
        "id_bin_language": "Naruto Anime_L9_-196727997_Portuguese"
      },
      {
        "author": "LMB Studio",
        "link_thumb": "https://live.staticflickr.com/65535/51682558051_1d51503592_o.gif",
        "link_bin": "https://github.com/lmbstudiocontact/mb4_60/raw/main/Naruto Anime_L9_-196727997_Russian.bin",
        "name_language": "Russian",
        "id_bin_language": "Naruto Anime_L9_-196727997_Russian"
      },
      {
        "author": "LMB Studio",
        "link_thumb": "https://live.staticflickr.com/65535/51681762767_625ea4c34d_o.gif",
        "link_bin": "https://github.com/lmbstudiocontact/mb4_60/raw/main/Naruto Anime_L9_-196727997_Spanish.bin",
        "name_language": "Spanish",
        "id_bin_language": "Naruto Anime_L9_-196727997_Spanish"
      }
    ],
    "array_tags": [
      "lmbstudio"
    ],
    "list_album": [
      {
        "id_album": "1894397991",
        "link_thumb": "https://live.staticflickr.com/65535/51683227214_451d0b735f_o.gif",
        "title": "Naruto Anime_L9"
      }
    ]
  },
  {
    "author": "LMB Studio",
    "link_thumb": "https://live.staticflickr.com/65535/51683448215_0203395e2e_o.gif",
    "link_bin": "https://github.com/lmbstudiocontact/mb4_60/raw/main/Naruto Anime_L9_-1983150983.bin",
    "id_bin": "Naruto Anime_L9_-1983150983",
    "list_language": [
      {
        "author": "LMB Studio",
        "link_thumb": "https://live.staticflickr.com/65535/51682817998_318d168824_o.gif",
        "link_bin": "https://github.com/lmbstudiocontact/mb4_60/raw/main/Naruto Anime_L9_-1983150983_English.bin",
        "name_language": "English",
        "id_bin_language": "Naruto Anime_L9_-1983150983_English"
      },
      {
        "author": "LMB Studio",
        "link_thumb": "https://live.staticflickr.com/65535/51682818288_cff972e973_o.gif",
        "link_bin": "https://github.com/lmbstudiocontact/mb4_60/raw/main/Naruto Anime_L9_-1983150983_Portuguese.bin",
        "name_language": "Portuguese",
        "id_bin_language": "Naruto Anime_L9_-1983150983_Portuguese"
      },
      {
        "author": "LMB Studio",
        "link_thumb": "https://live.staticflickr.com/65535/51683449225_7c53e9faf2_o.gif",
        "link_bin": "https://github.com/lmbstudiocontact/mb4_60/raw/main/Naruto Anime_L9_-1983150983_Russian.bin",
        "name_language": "Russian",
        "id_bin_language": "Naruto Anime_L9_-1983150983_Russian"
      },
      {
        "author": "LMB Studio",
        "link_thumb": "https://live.staticflickr.com/65535/51681764462_c5978c351e_o.gif",
        "link_bin": "https://github.com/lmbstudiocontact/mb4_60/raw/main/Naruto Anime_L9_-1983150983_Spanish.bin",
        "name_language": "Spanish",
        "id_bin_language": "Naruto Anime_L9_-1983150983_Spanish"
      }
    ],
    "array_tags": [
      "lmbstudio"
    ],
    "list_album": [
      {
        "id_album": "1894397991",
        "link_thumb": "https://live.staticflickr.com/65535/51683448215_0203395e2e_o.gif",
        "title": "Naruto Anime_L9"
      }
    ]
  },
  {
    "author": "LMB Studio",
    "link_thumb": "https://live.staticflickr.com/65535/51681764762_87cefd29ba_o.gif",
    "link_bin": "https://github.com/lmbstudiocontact/mb4_60/raw/main/Naruto Anime_L9_-2032963670.bin",
    "id_bin": "Naruto Anime_L9_-2032963670",
    "list_language": [
      {
        "author": "LMB Studio",
        "link_thumb": "https://live.staticflickr.com/65535/51682819723_6f1636c0e9_o.gif",
        "link_bin": "https://github.com/lmbstudiocontact/mb4_60/raw/main/Naruto Anime_L9_-2032963670_English.bin",
        "name_language": "English",
        "id_bin_language": "Naruto Anime_L9_-2032963670_English"
      },
      {
        "author": "LMB Studio",
        "link_thumb": "https://live.staticflickr.com/65535/51681765412_b2d6fd16bc_o.gif",
        "link_bin": "https://github.com/lmbstudiocontact/mb4_60/raw/main/Naruto Anime_L9_-2032963670_Portuguese.bin",
        "name_language": "Portuguese",
        "id_bin_language": "Naruto Anime_L9_-2032963670_Portuguese"
      },
      {
        "author": "LMB Studio",
        "link_thumb": "https://live.staticflickr.com/65535/51683450840_a1ecc7c652_o.gif",
        "link_bin": "https://github.com/lmbstudiocontact/mb4_60/raw/main/Naruto Anime_L9_-2032963670_Russian.bin",
        "name_language": "Russian",
        "id_bin_language": "Naruto Anime_L9_-2032963670_Russian"
      },
      {
        "author": "LMB Studio",
        "link_thumb": "https://live.staticflickr.com/65535/51681765902_cb5d4c8593_o.gif",
        "link_bin": "https://github.com/lmbstudiocontact/mb4_60/raw/main/Naruto Anime_L9_-2032963670_Spanish.bin",
        "name_language": "Spanish",
        "id_bin_language": "Naruto Anime_L9_-2032963670_Spanish"
      }
    ],
    "array_tags": [
      "lmbstudio"
    ],
    "list_album": [
      {
        "id_album": "1894397991",
        "link_thumb": "https://live.staticflickr.com/65535/51681764762_87cefd29ba_o.gif",
        "title": "Naruto Anime_L9"
      }
    ]
  },
  {
    "author": "LMB Studio",
    "link_thumb": "https://live.staticflickr.com/65535/51682562191_4df7bb95c7_o.gif",
    "link_bin": "https://github.com/lmbstudiocontact/mb4_60/raw/main/Naruto Anime_L9_-227912372.bin",
    "id_bin": "Naruto Anime_L9_-227912372",
    "list_language": [
      {
        "author": "LMB Studio",
        "link_thumb": "https://live.staticflickr.com/65535/51683451425_065d6b3901_o.gif",
        "link_bin": "https://github.com/lmbstudiocontact/mb4_60/raw/main/Naruto Anime_L9_-227912372_English.bin",
        "name_language": "English",
        "id_bin_language": "Naruto Anime_L9_-227912372_English"
      },
      {
        "author": "LMB Studio",
        "link_thumb": "https://live.staticflickr.com/65535/51681766677_4b66df79e5_o.gif",
        "link_bin": "https://github.com/lmbstudiocontact/mb4_60/raw/main/Naruto Anime_L9_-227912372_Portuguese.bin",
        "name_language": "Portuguese",
        "id_bin_language": "Naruto Anime_L9_-227912372_Portuguese"
      },
      {
        "author": "LMB Studio",
        "link_thumb": "https://live.staticflickr.com/65535/51683232534_abaf3d9013_o.gif",
        "link_bin": "https://github.com/lmbstudiocontact/mb4_60/raw/main/Naruto Anime_L9_-227912372_Russian.bin",
        "name_language": "Russian",
        "id_bin_language": "Naruto Anime_L9_-227912372_Russian"
      },
      {
        "author": "LMB Studio",
        "link_thumb": "https://live.staticflickr.com/65535/51683232894_d3ba8da96b_o.gif",
        "link_bin": "https://github.com/lmbstudiocontact/mb4_60/raw/main/Naruto Anime_L9_-227912372_Spanish.bin",
        "name_language": "Spanish",
        "id_bin_language": "Naruto Anime_L9_-227912372_Spanish"
      }
    ],
    "array_tags": [
      "lmbstudio"
    ],
    "list_album": [
      {
        "id_album": "1894397991",
        "link_thumb": "https://live.staticflickr.com/65535/51682562191_4df7bb95c7_o.gif",
        "title": "Naruto Anime_L9"
      }
    ]
  },
  {
    "author": "LMB Studio",
    "link_thumb": "https://live.staticflickr.com/65535/51683233134_b178551b36_o.gif",
    "link_bin": "https://github.com/lmbstudiocontact/mb4_60/raw/main/Naruto Anime_L9_-369030340.bin",
    "id_bin": "Naruto Anime_L9_-369030340",
    "list_language": [
      {
        "author": "LMB Studio",
        "link_thumb": "https://live.staticflickr.com/65535/51683233399_7a37779df4_o.gif",
        "link_bin": "https://github.com/lmbstudiocontact/mb4_60/raw/main/Naruto Anime_L9_-369030340_English.bin",
        "name_language": "English",
        "id_bin_language": "Naruto Anime_L9_-369030340_English"
      },
      {
        "author": "LMB Studio",
        "link_thumb": "https://live.staticflickr.com/65535/51683453125_06eefec6b7_o.gif",
        "link_bin": "https://github.com/lmbstudiocontact/mb4_60/raw/main/Naruto Anime_L9_-369030340_Portuguese.bin",
        "name_language": "Portuguese",
        "id_bin_language": "Naruto Anime_L9_-369030340_Portuguese"
      },
      {
        "author": "LMB Studio",
        "link_thumb": "https://live.staticflickr.com/65535/51682564196_cbb550da98_o.gif",
        "link_bin": "https://github.com/lmbstudiocontact/mb4_60/raw/main/Naruto Anime_L9_-369030340_Russian.bin",
        "name_language": "Russian",
        "id_bin_language": "Naruto Anime_L9_-369030340_Russian"
      },
      {
        "author": "LMB Studio",
        "link_thumb": "https://live.staticflickr.com/65535/51684232486_148169defc_o.gif",
        "link_bin": "https://github.com/lmbstudiocontact/mb4_60/raw/main/Naruto Anime_L9_-369030340_Spanish.bin",
        "name_language": "Spanish",
        "id_bin_language": "Naruto Anime_L9_-369030340_Spanish"
      }
    ],
    "array_tags": [
      "lmbstudio"
    ],
    "list_album": [
      {
        "id_album": "1894397991",
        "link_thumb": "https://live.staticflickr.com/65535/51683233134_b178551b36_o.gif",
        "title": "Naruto Anime_L9"
      }
    ]
  },
  {
    "author": "LMB Studio",
    "link_thumb": "https://live.staticflickr.com/65535/51682564491_f26d4532f7_o.gif",
    "link_bin": "https://github.com/lmbstudiocontact/mb4_60/raw/main/Naruto Anime_L9_-398080746.bin",
    "id_bin": "Naruto Anime_L9_-398080746",
    "list_language": [
      {
        "author": "LMB Studio",
        "link_thumb": "https://live.staticflickr.com/65535/51683234649_9fe26ab6db_o.gif",
        "link_bin": "https://github.com/lmbstudiocontact/mb4_60/raw/main/Naruto Anime_L9_-398080746_English.bin",
        "name_language": "English",
        "id_bin_language": "Naruto Anime_L9_-398080746_English"
      },
      {
        "author": "LMB Studio",
        "link_thumb": "https://live.staticflickr.com/65535/51682823623_aa5d8ed2fd_o.gif",
        "link_bin": "https://github.com/lmbstudiocontact/mb4_60/raw/main/Naruto Anime_L9_-398080746_Portuguese.bin",
        "name_language": "Portuguese",
        "id_bin_language": "Naruto Anime_L9_-398080746_Portuguese"
      },
      {
        "author": "LMB Studio",
        "link_thumb": "https://live.staticflickr.com/65535/51683235089_6b8918d688_o.gif",
        "link_bin": "https://github.com/lmbstudiocontact/mb4_60/raw/main/Naruto Anime_L9_-398080746_Russian.bin",
        "name_language": "Russian",
        "id_bin_language": "Naruto Anime_L9_-398080746_Russian"
      },
      {
        "author": "LMB Studio",
        "link_thumb": "https://live.staticflickr.com/65535/51683235349_dbddc2a8c4_o.gif",
        "link_bin": "https://github.com/lmbstudiocontact/mb4_60/raw/main/Naruto Anime_L9_-398080746_Spanish.bin",
        "name_language": "Spanish",
        "id_bin_language": "Naruto Anime_L9_-398080746_Spanish"
      }
    ],
    "array_tags": [
      "lmbstudio"
    ],
    "list_album": [
      {
        "id_album": "1894397991",
        "link_thumb": "https://live.staticflickr.com/65535/51682564491_f26d4532f7_o.gif",
        "title": "Naruto Anime_L9"
      }
    ]
  },
  {
    "author": "LMB Studio",
    "link_thumb": "https://live.staticflickr.com/65535/51683454975_67aefe198c_o.gif",
    "link_bin": "https://github.com/lmbstudiocontact/mb4_60/raw/main/Naruto Anime_L9_-662709780.bin",
    "id_bin": "Naruto Anime_L9_-662709780",
    "list_language": [
      {
        "author": "LMB Studio",
        "link_thumb": "https://live.staticflickr.com/65535/51683235784_eaaae89180_o.gif",
        "link_bin": "https://github.com/lmbstudiocontact/mb4_60/raw/main/Naruto Anime_L9_-662709780_English.bin",
        "name_language": "English",
        "id_bin_language": "Naruto Anime_L9_-662709780_English"
      },
      {
        "author": "LMB Studio",
        "link_thumb": "https://live.staticflickr.com/65535/51683236029_13c730502d_o.gif",
        "link_bin": "https://github.com/lmbstudiocontact/mb4_60/raw/main/Naruto Anime_L9_-662709780_Portuguese.bin",
        "name_language": "Portuguese",
        "id_bin_language": "Naruto Anime_L9_-662709780_Portuguese"
      },
      {
        "author": "LMB Studio",
        "link_thumb": "https://live.staticflickr.com/65535/51683455640_372f54f225_o.gif",
        "link_bin": "https://github.com/lmbstudiocontact/mb4_60/raw/main/Naruto Anime_L9_-662709780_Russian.bin",
        "name_language": "Russian",
        "id_bin_language": "Naruto Anime_L9_-662709780_Russian"
      },
      {
        "author": "LMB Studio",
        "link_thumb": "https://live.staticflickr.com/65535/51683236584_e6b9021c52_o.gif",
        "link_bin": "https://github.com/lmbstudiocontact/mb4_60/raw/main/Naruto Anime_L9_-662709780_Spanish.bin",
        "name_language": "Spanish",
        "id_bin_language": "Naruto Anime_L9_-662709780_Spanish"
      }
    ],
    "array_tags": [
      "lmbstudio"
    ],
    "list_album": [
      {
        "id_album": "1894397991",
        "link_thumb": "https://live.staticflickr.com/65535/51683454975_67aefe198c_o.gif",
        "title": "Naruto Anime_L9"
      }
    ]
  },
  {
    "author": "LMB Studio",
    "link_thumb": "https://live.staticflickr.com/65535/51682825533_3affc47e33_o.gif",
    "link_bin": "https://github.com/lmbstudiocontact/mb4_60/raw/main/Naruto Anime_L9_-89407115.bin",
    "id_bin": "Naruto Anime_L9_-89407115",
    "list_language": [
      {
        "author": "LMB Studio",
        "link_thumb": "https://live.staticflickr.com/65535/51683456490_1f6b95baf7_o.gif",
        "link_bin": "https://github.com/lmbstudiocontact/mb4_60/raw/main/Naruto Anime_L9_-89407115_English.bin",
        "name_language": "English",
        "id_bin_language": "Naruto Anime_L9_-89407115_English"
      },
      {
        "author": "LMB Studio",
        "link_thumb": "https://live.staticflickr.com/65535/51682825923_205446878a_o.gif",
        "link_bin": "https://github.com/lmbstudiocontact/mb4_60/raw/main/Naruto Anime_L9_-89407115_Portuguese.bin",
        "name_language": "Portuguese",
        "id_bin_language": "Naruto Anime_L9_-89407115_Portuguese"
      },
      {
        "author": "LMB Studio",
        "link_thumb": "https://live.staticflickr.com/65535/51681771777_24f00421e1_o.gif",
        "link_bin": "https://github.com/lmbstudiocontact/mb4_60/raw/main/Naruto Anime_L9_-89407115_Russian.bin",
        "name_language": "Russian",
        "id_bin_language": "Naruto Anime_L9_-89407115_Russian"
      },
      {
        "author": "LMB Studio",
        "link_thumb": "https://live.staticflickr.com/65535/51682567801_e5f96a2d31_o.gif",
        "link_bin": "https://github.com/lmbstudiocontact/mb4_60/raw/main/Naruto Anime_L9_-89407115_Spanish.bin",
        "name_language": "Spanish",
        "id_bin_language": "Naruto Anime_L9_-89407115_Spanish"
      }
    ],
    "array_tags": [
      "lmbstudio"
    ],
    "list_album": [
      {
        "id_album": "1894397991",
        "link_thumb": "https://live.staticflickr.com/65535/51682825533_3affc47e33_o.gif",
        "title": "Naruto Anime_L9"
      }
    ]
  },
  {
    "author": "LMB Studio",
    "link_thumb": "https://live.staticflickr.com/65535/51682568021_56992050bd_o.gif",
    "link_bin": "https://github.com/lmbstudiocontact/mb4_60/raw/main/Naruto Anime_L9_-934560909.bin",
    "id_bin": "Naruto Anime_L9_-934560909",
    "list_language": [
      {
        "author": "LMB Studio",
        "link_thumb": "https://live.staticflickr.com/65535/51681772492_237f686b29_o.gif",
        "link_bin": "https://github.com/lmbstudiocontact/mb4_60/raw/main/Naruto Anime_L9_-934560909_English.bin",
        "name_language": "English",
        "id_bin_language": "Naruto Anime_L9_-934560909_English"
      },
      {
        "author": "LMB Studio",
        "link_thumb": "https://live.staticflickr.com/65535/51682827243_145664a128_o.gif",
        "link_bin": "https://github.com/lmbstudiocontact/mb4_60/raw/main/Naruto Anime_L9_-934560909_Portuguese.bin",
        "name_language": "Portuguese",
        "id_bin_language": "Naruto Anime_L9_-934560909_Portuguese"
      },
      {
        "author": "LMB Studio",
        "link_thumb": "https://live.staticflickr.com/65535/51682827493_0929cc0228_o.gif",
        "link_bin": "https://github.com/lmbstudiocontact/mb4_60/raw/main/Naruto Anime_L9_-934560909_Russian.bin",
        "name_language": "Russian",
        "id_bin_language": "Naruto Anime_L9_-934560909_Russian"
      },
      {
        "author": "LMB Studio",
        "link_thumb": "https://live.staticflickr.com/65535/51682827783_6039836945_o.gif",
        "link_bin": "https://github.com/lmbstudiocontact/mb4_60/raw/main/Naruto Anime_L9_-934560909_Spanish.bin",
        "name_language": "Spanish",
        "id_bin_language": "Naruto Anime_L9_-934560909_Spanish"
      }
    ],
    "array_tags": [
      "lmbstudio"
    ],
    "list_album": [
      {
        "id_album": "1894397991",
        "link_thumb": "https://live.staticflickr.com/65535/51682568021_56992050bd_o.gif",
        "title": "Naruto Anime_L9"
      }
    ]
  },
  {
    "author": "LMB Studio",
    "link_thumb": "https://live.staticflickr.com/65535/51682569426_d53889677a_o.gif",
    "link_bin": "https://github.com/lmbstudiocontact/mb4_60/raw/main/Naruto Anime_L9_1420511599.bin",
    "id_bin": "Naruto Anime_L9_1420511599",
    "list_language": [
      {
        "author": "LMB Studio",
        "link_thumb": "https://live.staticflickr.com/65535/51682828248_63957cd022_o.gif",
        "link_bin": "https://github.com/lmbstudiocontact/mb4_60/raw/main/Naruto Anime_L9_1420511599_English.bin",
        "name_language": "English",
        "id_bin_language": "Naruto Anime_L9_1420511599_English"
      },
      {
        "author": "LMB Studio",
        "link_thumb": "https://live.staticflickr.com/65535/51683239704_24ae89635d_o.gif",
        "link_bin": "https://github.com/lmbstudiocontact/mb4_60/raw/main/Naruto Anime_L9_1420511599_Portuguese.bin",
        "name_language": "Portuguese",
        "id_bin_language": "Naruto Anime_L9_1420511599_Portuguese"
      },
      {
        "author": "LMB Studio",
        "link_thumb": "https://live.staticflickr.com/65535/51683239924_e54e8b8961_o.gif",
        "link_bin": "https://github.com/lmbstudiocontact/mb4_60/raw/main/Naruto Anime_L9_1420511599_Russian.bin",
        "name_language": "Russian",
        "id_bin_language": "Naruto Anime_L9_1420511599_Russian"
      },
      {
        "author": "LMB Studio",
        "link_thumb": "https://live.staticflickr.com/65535/51683240099_b78b562247_o.gif",
        "link_bin": "https://github.com/lmbstudiocontact/mb4_60/raw/main/Naruto Anime_L9_1420511599_Spanish.bin",
        "name_language": "Spanish",
        "id_bin_language": "Naruto Anime_L9_1420511599_Spanish"
      }
    ],
    "array_tags": [
      "lmbstudio"
    ],
    "list_album": [
      {
        "id_album": "1894397991",
        "link_thumb": "https://live.staticflickr.com/65535/51682569426_d53889677a_o.gif",
        "title": "Naruto Anime_L9"
      }
    ]
  },
  {
    "author": "LMB Studio",
    "link_thumb": "https://live.staticflickr.com/65535/51682570641_f0e3ce8c60_o.gif",
    "link_bin": "https://github.com/lmbstudiocontact/mb4_60/raw/main/Naruto Anime_L9_1447448187.bin",
    "id_bin": "Naruto Anime_L9_1447448187",
    "list_language": [
      {
        "author": "LMB Studio",
        "link_thumb": "https://live.staticflickr.com/65535/51682829368_33fa9a6cf2_o.gif",
        "link_bin": "https://github.com/lmbstudiocontact/mb4_60/raw/main/Naruto Anime_L9_1447448187_English.bin",
        "name_language": "English",
        "id_bin_language": "Naruto Anime_L9_1447448187_English"
      },
      {
        "author": "LMB Studio",
        "link_thumb": "https://live.staticflickr.com/65535/51683240924_996993a58f_o.gif",
        "link_bin": "https://github.com/lmbstudiocontact/mb4_60/raw/main/Naruto Anime_L9_1447448187_Portuguese.bin",
        "name_language": "Portuguese",
        "id_bin_language": "Naruto Anime_L9_1447448187_Portuguese"
      },
      {
        "author": "LMB Studio",
        "link_thumb": "https://live.staticflickr.com/65535/51682571261_d5b7525244_o.gif",
        "link_bin": "https://github.com/lmbstudiocontact/mb4_60/raw/main/Naruto Anime_L9_1447448187_Russian.bin",
        "name_language": "Russian",
        "id_bin_language": "Naruto Anime_L9_1447448187_Russian"
      },
      {
        "author": "LMB Studio",
        "link_thumb": "https://live.staticflickr.com/65535/51683460815_7389849739_o.gif",
        "link_bin": "https://github.com/lmbstudiocontact/mb4_60/raw/main/Naruto Anime_L9_1447448187_Spanish.bin",
        "name_language": "Spanish",
        "id_bin_language": "Naruto Anime_L9_1447448187_Spanish"
      }
    ],
    "array_tags": [
      "lmbstudio"
    ],
    "list_album": [
      {
        "id_album": "1894397991",
        "link_thumb": "https://live.staticflickr.com/65535/51682570641_f0e3ce8c60_o.gif",
        "title": "Naruto Anime_L9"
      }
    ]
  },
  {
    "author": "LMB Studio",
    "link_thumb": "https://live.staticflickr.com/65535/51683461070_7d436cf246_o.gif",
    "link_bin": "https://github.com/lmbstudiocontact/mb4_60/raw/main/Naruto Anime_L9_1447448188.bin",
    "id_bin": "Naruto Anime_L9_1447448188",
    "list_language": [
      {
        "author": "LMB Studio",
        "link_thumb": "https://live.staticflickr.com/65535/51682572031_f3d523c0c0_o.gif",
        "link_bin": "https://github.com/lmbstudiocontact/mb4_60/raw/main/Naruto Anime_L9_1447448188_English.bin",
        "name_language": "English",
        "id_bin_language": "Naruto Anime_L9_1447448188_English"
      },
      {
        "author": "LMB Studio",
        "link_thumb": "https://live.staticflickr.com/65535/51683461595_ab7c8fe84d_o.gif",
        "link_bin": "https://github.com/lmbstudiocontact/mb4_60/raw/main/Naruto Anime_L9_1447448188_Portuguese.bin",
        "name_language": "Portuguese",
        "id_bin_language": "Naruto Anime_L9_1447448188_Portuguese"
      },
      {
        "author": "LMB Studio",
        "link_thumb": "https://live.staticflickr.com/65535/51683461770_8943164610_o.gif",
        "link_bin": "https://github.com/lmbstudiocontact/mb4_60/raw/main/Naruto Anime_L9_1447448188_Russian.bin",
        "name_language": "Russian",
        "id_bin_language": "Naruto Anime_L9_1447448188_Russian"
      },
      {
        "author": "LMB Studio",
        "link_thumb": "https://live.staticflickr.com/65535/51683462200_ffa3462f8a_o.gif",
        "link_bin": "https://github.com/lmbstudiocontact/mb4_60/raw/main/Naruto Anime_L9_1447448188_Spanish.bin",
        "name_language": "Spanish",
        "id_bin_language": "Naruto Anime_L9_1447448188_Spanish"
      }
    ],
    "array_tags": [
      "lmbstudio"
    ],
    "list_album": [
      {
        "id_album": "1894397991",
        "link_thumb": "https://live.staticflickr.com/65535/51683461070_7d436cf246_o.gif",
        "title": "Naruto Anime_L9"
      }
    ]
  },
  {
    "author": "LMB Studio",
    "link_thumb": "https://live.staticflickr.com/65535/51682573096_8646f5ece7_o.gif",
    "link_bin": "https://github.com/lmbstudiocontact/mb4_60/raw/main/Naruto Anime_L9_1447448189.bin",
    "id_bin": "Naruto Anime_L9_1447448189",
    "list_language": [
      {
        "author": "LMB Studio",
        "link_thumb": "https://live.staticflickr.com/65535/51683462695_b3aeabedb7_o.gif",
        "link_bin": "https://github.com/lmbstudiocontact/mb4_60/raw/main/Naruto Anime_L9_1447448189_English.bin",
        "name_language": "English",
        "id_bin_language": "Naruto Anime_L9_1447448189_English"
      },
      {
        "author": "LMB Studio",
        "link_thumb": "https://live.staticflickr.com/65535/51683462940_925d8e6a2a_o.gif",
        "link_bin": "https://github.com/lmbstudiocontact/mb4_60/raw/main/Naruto Anime_L9_1447448189_Portuguese.bin",
        "name_language": "Portuguese",
        "id_bin_language": "Naruto Anime_L9_1447448189_Portuguese"
      },
      {
        "author": "LMB Studio",
        "link_thumb": "https://live.staticflickr.com/65535/51682573851_8ebd62c52d_o.gif",
        "link_bin": "https://github.com/lmbstudiocontact/mb4_60/raw/main/Naruto Anime_L9_1447448189_Russian.bin",
        "name_language": "Russian",
        "id_bin_language": "Naruto Anime_L9_1447448189_Russian"
      },
      {
        "author": "LMB Studio",
        "link_thumb": "https://live.staticflickr.com/65535/51683463520_b3f9ca587d_o.gif",
        "link_bin": "https://github.com/lmbstudiocontact/mb4_60/raw/main/Naruto Anime_L9_1447448189_Spanish.bin",
        "name_language": "Spanish",
        "id_bin_language": "Naruto Anime_L9_1447448189_Spanish"
      }
    ],
    "array_tags": [
      "lmbstudio"
    ],
    "list_album": [
      {
        "id_album": "1894397991",
        "link_thumb": "https://live.staticflickr.com/65535/51682573096_8646f5ece7_o.gif",
        "title": "Naruto Anime_L9"
      }
    ]
  },
  {
    "author": "LMB Studio",
    "link_thumb": "https://live.staticflickr.com/65535/51682832703_26fb126ba1_o.gif",
    "link_bin": "https://github.com/lmbstudiocontact/mb4_60/raw/main/Naruto Anime_L9_1447448253.bin",
    "id_bin": "Naruto Anime_L9_1447448253",
    "list_language": [
      {
        "author": "LMB Studio",
        "link_thumb": "https://live.staticflickr.com/65535/51682832908_91909330b5_o.gif",
        "link_bin": "https://github.com/lmbstudiocontact/mb4_60/raw/main/Naruto Anime_L9_1447448253_English.bin",
        "name_language": "English",
        "id_bin_language": "Naruto Anime_L9_1447448253_English"
      },
      {
        "author": "LMB Studio",
        "link_thumb": "https://live.staticflickr.com/65535/51682574816_353bb3a9e2_o.gif",
        "link_bin": "https://github.com/lmbstudiocontact/mb4_60/raw/main/Naruto Anime_L9_1447448253_Portuguese.bin",
        "name_language": "Portuguese",
        "id_bin_language": "Naruto Anime_L9_1447448253_Portuguese"
      },
      {
        "author": "LMB Studio",
        "link_thumb": "https://live.staticflickr.com/65535/51682575096_7a702539bb_o.gif",
        "link_bin": "https://github.com/lmbstudiocontact/mb4_60/raw/main/Naruto Anime_L9_1447448253_Russian.bin",
        "name_language": "Russian",
        "id_bin_language": "Naruto Anime_L9_1447448253_Russian"
      },
      {
        "author": "LMB Studio",
        "link_thumb": "https://live.staticflickr.com/65535/51681779242_8709df95fa_o.gif",
        "link_bin": "https://github.com/lmbstudiocontact/mb4_60/raw/main/Naruto Anime_L9_1447448253_Spanish.bin",
        "name_language": "Spanish",
        "id_bin_language": "Naruto Anime_L9_1447448253_Spanish"
      }
    ],
    "array_tags": [
      "lmbstudio"
    ],
    "list_album": [
      {
        "id_album": "1894397991",
        "link_thumb": "https://live.staticflickr.com/65535/51682832703_26fb126ba1_o.gif",
        "title": "Naruto Anime_L9"
      }
    ]
  },
  {
    "author": "LMB Studio",
    "link_thumb": "https://live.staticflickr.com/65535/51682833773_d608a13136_o.gif",
    "link_bin": "https://github.com/lmbstudiocontact/mb4_60/raw/main/Naruto Anime_L9_1873295009.bin",
    "id_bin": "Naruto Anime_L9_1873295009",
    "list_language": [
      {
        "author": "LMB Studio",
        "link_thumb": "https://live.staticflickr.com/65535/51683245479_7f1e8f8188_o.gif",
        "link_bin": "https://github.com/lmbstudiocontact/mb4_60/raw/main/Naruto Anime_L9_1873295009_English.bin",
        "name_language": "English",
        "id_bin_language": "Naruto Anime_L9_1873295009_English"
      },
      {
        "author": "LMB Studio",
        "link_thumb": "https://live.staticflickr.com/65535/51682834133_7341de1449_o.gif",
        "link_bin": "https://github.com/lmbstudiocontact/mb4_60/raw/main/Naruto Anime_L9_1873295009_Portuguese.bin",
        "name_language": "Portuguese",
        "id_bin_language": "Naruto Anime_L9_1873295009_Portuguese"
      },
      {
        "author": "LMB Studio",
        "link_thumb": "https://live.staticflickr.com/65535/51681779982_1ac5e88716_o.gif",
        "link_bin": "https://github.com/lmbstudiocontact/mb4_60/raw/main/Naruto Anime_L9_1873295009_Russian.bin",
        "name_language": "Russian",
        "id_bin_language": "Naruto Anime_L9_1873295009_Russian"
      },
      {
        "author": "LMB Studio",
        "link_thumb": "https://live.staticflickr.com/65535/51683246054_546ab2ec96_o.gif",
        "link_bin": "https://github.com/lmbstudiocontact/mb4_60/raw/main/Naruto Anime_L9_1873295009_Spanish.bin",
        "name_language": "Spanish",
        "id_bin_language": "Naruto Anime_L9_1873295009_Spanish"
      }
    ],
    "array_tags": [
      "lmbstudio"
    ],
    "list_album": [
      {
        "id_album": "1894397991",
        "link_thumb": "https://live.staticflickr.com/65535/51682833773_d608a13136_o.gif",
        "title": "Naruto Anime_L9"
      }
    ]
  },
  {
    "author": "LMB Studio",
    "link_thumb": "https://live.staticflickr.com/65535/51682576406_808e32810e_o.gif",
    "link_bin": "https://github.com/lmbstudiocontact/mb4_60/raw/main/Naruto Anime_L9_227608054.bin",
    "id_bin": "Naruto Anime_L9_227608054",
    "list_language": [
      {
        "author": "LMB Studio",
        "link_thumb": "https://live.staticflickr.com/65535/51682834798_abc404cce7_o.gif",
        "link_bin": "https://github.com/lmbstudiocontact/mb4_60/raw/main/Naruto Anime_L9_227608054_English.bin",
        "name_language": "English",
        "id_bin_language": "Naruto Anime_L9_227608054_English"
      },
      {
        "author": "LMB Studio",
        "link_thumb": "https://live.staticflickr.com/65535/51681780772_1d3411365b_o.gif",
        "link_bin": "https://github.com/lmbstudiocontact/mb4_60/raw/main/Naruto Anime_L9_227608054_Portuguese.bin",
        "name_language": "Portuguese",
        "id_bin_language": "Naruto Anime_L9_227608054_Portuguese"
      },
      {
        "author": "LMB Studio",
        "link_thumb": "https://live.staticflickr.com/65535/51683246914_cda2796269_o.gif",
        "link_bin": "https://github.com/lmbstudiocontact/mb4_60/raw/main/Naruto Anime_L9_227608054_Russian.bin",
        "name_language": "Russian",
        "id_bin_language": "Naruto Anime_L9_227608054_Russian"
      },
      {
        "author": "LMB Studio",
        "link_thumb": "https://live.staticflickr.com/65535/51683466845_6700db4ab4_o.gif",
        "link_bin": "https://github.com/lmbstudiocontact/mb4_60/raw/main/Naruto Anime_L9_227608054_Spanish.bin",
        "name_language": "Spanish",
        "id_bin_language": "Naruto Anime_L9_227608054_Spanish"
      }
    ],
    "array_tags": [
      "lmbstudio"
    ],
    "list_album": [
      {
        "id_album": "1894397991",
        "link_thumb": "https://live.staticflickr.com/65535/51682576406_808e32810e_o.gif",
        "title": "Naruto Anime_L9"
      }
    ]
  },
  {
    "author": "LMB Studio",
    "link_thumb": "https://live.staticflickr.com/65535/51682577471_82e0842fb0_o.gif",
    "link_bin": "https://github.com/lmbstudiocontact/mb4_60/raw/main/Naruto Anime_L9_263817851.bin",
    "id_bin": "Naruto Anime_L9_263817851",
    "list_language": [
      {
        "author": "LMB Studio",
        "link_thumb": "https://live.staticflickr.com/65535/51682577641_0fdcf59682_o.gif",
        "link_bin": "https://github.com/lmbstudiocontact/mb4_60/raw/main/Naruto Anime_L9_263817851_English.bin",
        "name_language": "English",
        "id_bin_language": "Naruto Anime_L9_263817851_English"
      },
      {
        "author": "LMB Studio",
        "link_thumb": "https://live.staticflickr.com/65535/51682835978_5da2df021a_o.gif",
        "link_bin": "https://github.com/lmbstudiocontact/mb4_60/raw/main/Naruto Anime_L9_263817851_Portuguese.bin",
        "name_language": "Portuguese",
        "id_bin_language": "Naruto Anime_L9_263817851_Portuguese"
      },
      {
        "author": "LMB Studio",
        "link_thumb": "https://live.staticflickr.com/65535/51682578076_38ffaf2258_o.gif",
        "link_bin": "https://github.com/lmbstudiocontact/mb4_60/raw/main/Naruto Anime_L9_263817851_Russian.bin",
        "name_language": "Russian",
        "id_bin_language": "Naruto Anime_L9_263817851_Russian"
      },
      {
        "author": "LMB Studio",
        "link_thumb": "https://live.staticflickr.com/65535/51681782557_72ca400e42_o.gif",
        "link_bin": "https://github.com/lmbstudiocontact/mb4_60/raw/main/Naruto Anime_L9_263817851_Spanish.bin",
        "name_language": "Spanish",
        "id_bin_language": "Naruto Anime_L9_263817851_Spanish"
      }
    ],
    "array_tags": [
      "lmbstudio"
    ],
    "list_album": [
      {
        "id_album": "1894397991",
        "link_thumb": "https://live.staticflickr.com/65535/51682577471_82e0842fb0_o.gif",
        "title": "Naruto Anime_L9"
      }
    ]
  },
  {
    "author": "LMB Studio",
    "link_thumb": "https://live.staticflickr.com/65535/51683468320_c0d42d39e2_o.gif",
    "link_bin": "https://github.com/lmbstudiocontact/mb4_60/raw/main/Naruto Anime_L9_263817852.bin",
    "id_bin": "Naruto Anime_L9_263817852",
    "list_language": [
      {
        "author": "LMB Studio",
        "link_thumb": "https://live.staticflickr.com/65535/51681783052_9150a66994_o.gif",
        "link_bin": "https://github.com/lmbstudiocontact/mb4_60/raw/main/Naruto Anime_L9_263817852_English.bin",
        "name_language": "English",
        "id_bin_language": "Naruto Anime_L9_263817852_English"
      },
      {
        "author": "LMB Studio",
        "link_thumb": "https://live.staticflickr.com/65535/51681783282_2791fcc687_o.gif",
        "link_bin": "https://github.com/lmbstudiocontact/mb4_60/raw/main/Naruto Anime_L9_263817852_Portuguese.bin",
        "name_language": "Portuguese",
        "id_bin_language": "Naruto Anime_L9_263817852_Portuguese"
      },
      {
        "author": "LMB Studio",
        "link_thumb": "https://live.staticflickr.com/65535/51681783492_d88c5e6125_o.gif",
        "link_bin": "https://github.com/lmbstudiocontact/mb4_60/raw/main/Naruto Anime_L9_263817852_Russian.bin",
        "name_language": "Russian",
        "id_bin_language": "Naruto Anime_L9_263817852_Russian"
      },
      {
        "author": "LMB Studio",
        "link_thumb": "https://live.staticflickr.com/65535/51682579456_3980e61ac3_o.gif",
        "link_bin": "https://github.com/lmbstudiocontact/mb4_60/raw/main/Naruto Anime_L9_263817852_Spanish.bin",
        "name_language": "Spanish",
        "id_bin_language": "Naruto Anime_L9_263817852_Spanish"
      }
    ],
    "array_tags": [
      "lmbstudio"
    ],
    "list_album": [
      {
        "id_album": "1894397991",
        "link_thumb": "https://live.staticflickr.com/65535/51683468320_c0d42d39e2_o.gif",
        "title": "Naruto Anime_L9"
      }
    ]
  },
  {
    "author": "LMB Studio",
    "link_thumb": "https://live.staticflickr.com/65535/51681783907_23c7b79f8b_o.gif",
    "link_bin": "https://github.com/lmbstudiocontact/mb4_60/raw/main/Naruto Anime_L9_264464359.bin",
    "id_bin": "Naruto Anime_L9_264464359",
    "list_language": [
      {
        "author": "LMB Studio",
        "link_thumb": "https://live.staticflickr.com/65535/51682579901_1ef9ab22f2_o.gif",
        "link_bin": "https://github.com/lmbstudiocontact/mb4_60/raw/main/Naruto Anime_L9_264464359_English.bin",
        "name_language": "English",
        "id_bin_language": "Naruto Anime_L9_264464359_English"
      },
      {
        "author": "LMB Studio",
        "link_thumb": "https://live.staticflickr.com/65535/51683469775_36820039da_o.gif",
        "link_bin": "https://github.com/lmbstudiocontact/mb4_60/raw/main/Naruto Anime_L9_264464359_Portuguese.bin",
        "name_language": "Portuguese",
        "id_bin_language": "Naruto Anime_L9_264464359_Portuguese"
      },
      {
        "author": "LMB Studio",
        "link_thumb": "https://live.staticflickr.com/65535/51681784577_7c8f39e648_o.gif",
        "link_bin": "https://github.com/lmbstudiocontact/mb4_60/raw/main/Naruto Anime_L9_264464359_Russian.bin",
        "name_language": "Russian",
        "id_bin_language": "Naruto Anime_L9_264464359_Russian"
      },
      {
        "author": "LMB Studio",
        "link_thumb": "https://live.staticflickr.com/65535/51682580566_9350b8999d_o.gif",
        "link_bin": "https://github.com/lmbstudiocontact/mb4_60/raw/main/Naruto Anime_L9_264464359_Spanish.bin",
        "name_language": "Spanish",
        "id_bin_language": "Naruto Anime_L9_264464359_Spanish"
      }
    ],
    "array_tags": [
      "lmbstudio"
    ],
    "list_album": [
      {
        "id_album": "1894397991",
        "link_thumb": "https://live.staticflickr.com/65535/51681783907_23c7b79f8b_o.gif",
        "title": "Naruto Anime_L9"
      }
    ]
  },
  {
    "author": "LMB Studio",
    "link_thumb": "https://live.staticflickr.com/65535/51683250829_82a6893258_o.gif",
    "link_bin": "https://github.com/lmbstudiocontact/mb4_60/raw/main/Naruto Anime_L9_278283010.bin",
    "id_bin": "Naruto Anime_L9_278283010",
    "list_language": [
      {
        "author": "LMB Studio",
        "link_thumb": "https://live.staticflickr.com/65535/51681785277_7541cdbccd_o.gif",
        "link_bin": "https://github.com/lmbstudiocontact/mb4_60/raw/main/Naruto Anime_L9_278283010_English.bin",
        "name_language": "English",
        "id_bin_language": "Naruto Anime_L9_278283010_English"
      },
      {
        "author": "LMB Studio",
        "link_thumb": "https://live.staticflickr.com/65535/51683251384_dd23877554_o.gif",
        "link_bin": "https://github.com/lmbstudiocontact/mb4_60/raw/main/Naruto Anime_L9_278283010_Portuguese.bin",
        "name_language": "Portuguese",
        "id_bin_language": "Naruto Anime_L9_278283010_Portuguese"
      },
      {
        "author": "LMB Studio",
        "link_thumb": "https://live.staticflickr.com/65535/51682581611_78345a67b6_o.gif",
        "link_bin": "https://github.com/lmbstudiocontact/mb4_60/raw/main/Naruto Anime_L9_278283010_Russian.bin",
        "name_language": "Russian",
        "id_bin_language": "Naruto Anime_L9_278283010_Russian"
      },
      {
        "author": "LMB Studio",
        "link_thumb": "https://live.staticflickr.com/65535/51683251894_d3f254930b_o.gif",
        "link_bin": "https://github.com/lmbstudiocontact/mb4_60/raw/main/Naruto Anime_L9_278283010_Spanish.bin",
        "name_language": "Spanish",
        "id_bin_language": "Naruto Anime_L9_278283010_Spanish"
      }
    ],
    "array_tags": [
      "lmbstudio"
    ],
    "list_album": [
      {
        "id_album": "1894397991",
        "link_thumb": "https://live.staticflickr.com/65535/51683250829_82a6893258_o.gif",
        "title": "Naruto Anime_L9"
      }
    ]
  },
  {
    "author": "LMB Studio",
    "link_thumb": "https://live.staticflickr.com/65535/51683471780_a9df069699_o.gif",
    "link_bin": "https://github.com/lmbstudiocontact/mb4_60/raw/main/Naruto Anime_L9_316974914.bin",
    "id_bin": "Naruto Anime_L9_316974914",
    "list_language": [
      {
        "author": "LMB Studio",
        "link_thumb": "https://live.staticflickr.com/65535/51683252254_79c0086840_o.gif",
        "link_bin": "https://github.com/lmbstudiocontact/mb4_60/raw/main/Naruto Anime_L9_316974914_English.bin",
        "name_language": "English",
        "id_bin_language": "Naruto Anime_L9_316974914_English"
      },
      {
        "author": "LMB Studio",
        "link_thumb": "https://live.staticflickr.com/65535/51682582586_5d32699b21_o.gif",
        "link_bin": "https://github.com/lmbstudiocontact/mb4_60/raw/main/Naruto Anime_L9_316974914_Portuguese.bin",
        "name_language": "Portuguese",
        "id_bin_language": "Naruto Anime_L9_316974914_Portuguese"
      },
      {
        "author": "LMB Studio",
        "link_thumb": "https://live.staticflickr.com/65535/51682582816_40f8522095_o.gif",
        "link_bin": "https://github.com/lmbstudiocontact/mb4_60/raw/main/Naruto Anime_L9_316974914_Russian.bin",
        "name_language": "Russian",
        "id_bin_language": "Naruto Anime_L9_316974914_Russian"
      },
      {
        "author": "LMB Studio",
        "link_thumb": "https://live.staticflickr.com/65535/51681787252_d55ab9ef6d_o.gif",
        "link_bin": "https://github.com/lmbstudiocontact/mb4_60/raw/main/Naruto Anime_L9_316974914_Spanish.bin",
        "name_language": "Spanish",
        "id_bin_language": "Naruto Anime_L9_316974914_Spanish"
      }
    ],
    "array_tags": [
      "lmbstudio"
    ],
    "list_album": [
      {
        "id_album": "1894397991",
        "link_thumb": "https://live.staticflickr.com/65535/51683471780_a9df069699_o.gif",
        "title": "Naruto Anime_L9"
      }
    ]
  },
  {
    "author": "LMB Studio",
    "link_thumb": "https://live.staticflickr.com/65535/51682841503_d3629eb92a_o.gif",
    "link_bin": "https://github.com/lmbstudiocontact/mb4_60/raw/main/Naruto Anime_L9_887373446.bin",
    "id_bin": "Naruto Anime_L9_887373446",
    "list_language": [
      {
        "author": "LMB Studio",
        "link_thumb": "https://live.staticflickr.com/65535/51682583501_2747d2cc48_o.gif",
        "link_bin": "https://github.com/lmbstudiocontact/mb4_60/raw/main/Naruto Anime_L9_887373446_English.bin",
        "name_language": "English",
        "id_bin_language": "Naruto Anime_L9_887373446_English"
      },
      {
        "author": "LMB Studio",
        "link_thumb": "https://live.staticflickr.com/65535/51681787987_491ed9d2af_o.gif",
        "link_bin": "https://github.com/lmbstudiocontact/mb4_60/raw/main/Naruto Anime_L9_887373446_Portuguese.bin",
        "name_language": "Portuguese",
        "id_bin_language": "Naruto Anime_L9_887373446_Portuguese"
      },
      {
        "author": "LMB Studio",
        "link_thumb": "https://live.staticflickr.com/65535/51681788327_1618f6ed49_o.gif",
        "link_bin": "https://github.com/lmbstudiocontact/mb4_60/raw/main/Naruto Anime_L9_887373446_Russian.bin",
        "name_language": "Russian",
        "id_bin_language": "Naruto Anime_L9_887373446_Russian"
      },
      {
        "author": "LMB Studio",
        "link_thumb": "https://live.staticflickr.com/65535/51683254319_9663c8b154_o.gif",
        "link_bin": "https://github.com/lmbstudiocontact/mb4_60/raw/main/Naruto Anime_L9_887373446_Spanish.bin",
        "name_language": "Spanish",
        "id_bin_language": "Naruto Anime_L9_887373446_Spanish"
      }
    ],
    "array_tags": [
      "lmbstudio"
    ],
    "list_album": [
      {
        "id_album": "1894397991",
        "link_thumb": "https://live.staticflickr.com/65535/51682841503_d3629eb92a_o.gif",
        "title": "Naruto Anime_L9"
      }
    ]
  },
  {
    "author": "LMB Studio",
    "link_thumb": "https://live.staticflickr.com/65535/51682843148_6ebd3cce2d_o.gif",
    "link_bin": "https://github.com/lmbstudiocontact/mb4_60/raw/main/Naruto Anime_L9_916347553.bin",
    "id_bin": "Naruto Anime_L9_916347553",
    "list_language": [
      {
        "author": "LMB Studio",
        "link_thumb": "https://live.staticflickr.com/65535/51682843508_56250d1cfb_o.gif",
        "link_bin": "https://github.com/lmbstudiocontact/mb4_60/raw/main/Naruto Anime_L9_916347553_English.bin",
        "name_language": "English",
        "id_bin_language": "Naruto Anime_L9_916347553_English"
      },
      {
        "author": "LMB Studio",
        "link_thumb": "https://live.staticflickr.com/65535/51683255219_dfbae07dfa_o.gif",
        "link_bin": "https://github.com/lmbstudiocontact/mb4_60/raw/main/Naruto Anime_L9_916347553_Portuguese.bin",
        "name_language": "Portuguese",
        "id_bin_language": "Naruto Anime_L9_916347553_Portuguese"
      },
      {
        "author": "LMB Studio",
        "link_thumb": "https://live.staticflickr.com/65535/51682843908_b6d6433494_o.gif",
        "link_bin": "https://github.com/lmbstudiocontact/mb4_60/raw/main/Naruto Anime_L9_916347553_Russian.bin",
        "name_language": "Russian",
        "id_bin_language": "Naruto Anime_L9_916347553_Russian"
      },
      {
        "author": "LMB Studio",
        "link_thumb": "https://live.staticflickr.com/65535/51683255729_d123396f75_o.gif",
        "link_bin": "https://github.com/lmbstudiocontact/mb4_60/raw/main/Naruto Anime_L9_916347553_Spanish.bin",
        "name_language": "Spanish",
        "id_bin_language": "Naruto Anime_L9_916347553_Spanish"
      }
    ],
    "array_tags": [
      "lmbstudio"
    ],
    "list_album": [
      {
        "id_album": "1894397991",
        "link_thumb": "https://live.staticflickr.com/65535/51682843148_6ebd3cce2d_o.gif",
        "title": "Naruto Anime_L9"
      }
    ]
  },
  {
    "author": "LMB Studio",
    "link_thumb": "https://live.staticflickr.com/65535/51683255944_0992b86d2b_o.gif",
    "link_bin": "https://github.com/lmbstudiocontact/mb4_60/raw/main/One Piece Anime_L10_-1071653354.bin",
    "id_bin": "One Piece Anime_L10_-1071653354",
    "list_language": [
      {
        "author": "LMB Studio",
        "link_thumb": "https://live.staticflickr.com/65535/51682844793_2e4bb3f80a_o.gif",
        "link_bin": "https://github.com/lmbstudiocontact/mb4_60/raw/main/One Piece Anime_L10_-1071653354_English.bin",
        "name_language": "English",
        "id_bin_language": "One Piece Anime_L10_-1071653354_English"
      },
      {
        "author": "LMB Studio",
        "link_thumb": "https://live.staticflickr.com/65535/51681790832_eb179f0d2e_o.gif",
        "link_bin": "https://github.com/lmbstudiocontact/mb4_60/raw/main/One Piece Anime_L10_-1071653354_Portuguese.bin",
        "name_language": "Portuguese",
        "id_bin_language": "One Piece Anime_L10_-1071653354_Portuguese"
      },
      {
        "author": "LMB Studio",
        "link_thumb": "https://live.staticflickr.com/65535/51683256659_18cc37d979_o.gif",
        "link_bin": "https://github.com/lmbstudiocontact/mb4_60/raw/main/One Piece Anime_L10_-1071653354_Russian.bin",
        "name_language": "Russian",
        "id_bin_language": "One Piece Anime_L10_-1071653354_Russian"
      },
      {
        "author": "LMB Studio",
        "link_thumb": "https://live.staticflickr.com/65535/51682845598_67e43f5f7a_o.gif",
        "link_bin": "https://github.com/lmbstudiocontact/mb4_60/raw/main/One Piece Anime_L10_-1071653354_Spanish.bin",
        "name_language": "Spanish",
        "id_bin_language": "One Piece Anime_L10_-1071653354_Spanish"
      }
    ],
    "array_tags": [
      "lmbstudio"
    ],
    "list_album": [
      {
        "id_album": "-1054518188",
        "link_thumb": "https://live.staticflickr.com/65535/51683255944_0992b86d2b_o.gif",
        "title": "One Piece Anime_L10"
      }
    ]
  },
  {
    "author": "LMB Studio",
    "link_thumb": "https://live.staticflickr.com/65535/51681791672_10fd18eaa2_o.gif",
    "link_bin": "https://github.com/lmbstudiocontact/mb4_60/raw/main/One Piece Anime_L10_-1088670595.bin",
    "id_bin": "One Piece Anime_L10_-1088670595",
    "list_language": [
      {
        "author": "LMB Studio",
        "link_thumb": "https://live.staticflickr.com/65535/51683257544_28328183ec_o.gif",
        "link_bin": "https://github.com/lmbstudiocontact/mb4_60/raw/main/One Piece Anime_L10_-1088670595_English.bin",
        "name_language": "English",
        "id_bin_language": "One Piece Anime_L10_-1088670595_English"
      },
      {
        "author": "LMB Studio",
        "link_thumb": "https://live.staticflickr.com/65535/51683477620_0938e0b5e7_o.gif",
        "link_bin": "https://github.com/lmbstudiocontact/mb4_60/raw/main/One Piece Anime_L10_-1088670595_Portuguese.bin",
        "name_language": "Portuguese",
        "id_bin_language": "One Piece Anime_L10_-1088670595_Portuguese"
      },
      {
        "author": "LMB Studio",
        "link_thumb": "https://live.staticflickr.com/65535/51683258029_b49f2b7ef5_o.gif",
        "link_bin": "https://github.com/lmbstudiocontact/mb4_60/raw/main/One Piece Anime_L10_-1088670595_Russian.bin",
        "name_language": "Russian",
        "id_bin_language": "One Piece Anime_L10_-1088670595_Russian"
      },
      {
        "author": "LMB Studio",
        "link_thumb": "https://live.staticflickr.com/65535/51683478125_00e0ebe886_o.gif",
        "link_bin": "https://github.com/lmbstudiocontact/mb4_60/raw/main/One Piece Anime_L10_-1088670595_Spanish.bin",
        "name_language": "Spanish",
        "id_bin_language": "One Piece Anime_L10_-1088670595_Spanish"
      }
    ],
    "array_tags": [
      "lmbstudio"
    ],
    "list_album": [
      {
        "id_album": "-1054518188",
        "link_thumb": "https://live.staticflickr.com/65535/51681791672_10fd18eaa2_o.gif",
        "title": "One Piece Anime_L10"
      }
    ]
  },
  {
    "author": "LMB Studio",
    "link_thumb": "https://live.staticflickr.com/65535/51682847343_84f0713f80_o.gif",
    "link_bin": "https://github.com/lmbstudiocontact/mb4_60/raw/main/One Piece Anime_L10_-1104136270.bin",
    "id_bin": "One Piece Anime_L10_-1104136270",
    "list_language": [
      {
        "author": "LMB Studio",
        "link_thumb": "https://live.staticflickr.com/65535/51683478540_91e8ab78b4_o.gif",
        "link_bin": "https://github.com/lmbstudiocontact/mb4_60/raw/main/One Piece Anime_L10_-1104136270_English.bin",
        "name_language": "English",
        "id_bin_language": "One Piece Anime_L10_-1104136270_English"
      },
      {
        "author": "LMB Studio",
        "link_thumb": "https://live.staticflickr.com/65535/51682589136_91ecabd528_o.gif",
        "link_bin": "https://github.com/lmbstudiocontact/mb4_60/raw/main/One Piece Anime_L10_-1104136270_Portuguese.bin",
        "name_language": "Portuguese",
        "id_bin_language": "One Piece Anime_L10_-1104136270_Portuguese"
      },
      {
        "author": "LMB Studio",
        "link_thumb": "https://live.staticflickr.com/65535/51683479000_a552b1062d_o.gif",
        "link_bin": "https://github.com/lmbstudiocontact/mb4_60/raw/main/One Piece Anime_L10_-1104136270_Russian.bin",
        "name_language": "Russian",
        "id_bin_language": "One Piece Anime_L10_-1104136270_Russian"
      },
      {
        "author": "LMB Studio",
        "link_thumb": "https://live.staticflickr.com/65535/51683259409_16517354ac_o.gif",
        "link_bin": "https://github.com/lmbstudiocontact/mb4_60/raw/main/One Piece Anime_L10_-1104136270_Spanish.bin",
        "name_language": "Spanish",
        "id_bin_language": "One Piece Anime_L10_-1104136270_Spanish"
      }
    ],
    "array_tags": [
      "lmbstudio"
    ],
    "list_album": [
      {
        "id_album": "-1054518188",
        "link_thumb": "https://live.staticflickr.com/65535/51682847343_84f0713f80_o.gif",
        "title": "One Piece Anime_L10"
      }
    ]
  },
  {
    "author": "LMB Studio",
    "link_thumb": "https://live.staticflickr.com/65535/51682848338_2e6ae5e56f_o.gif",
    "link_bin": "https://github.com/lmbstudiocontact/mb4_60/raw/main/One Piece Anime_L10_-1110487607.bin",
    "id_bin": "One Piece Anime_L10_-1110487607",
    "list_language": [
      {
        "author": "LMB Studio",
        "link_thumb": "https://live.staticflickr.com/65535/51682590006_56eb180e85_o.gif",
        "link_bin": "https://github.com/lmbstudiocontact/mb4_60/raw/main/One Piece Anime_L10_-1110487607_English.bin",
        "name_language": "English",
        "id_bin_language": "One Piece Anime_L10_-1110487607_English"
      },
      {
        "author": "LMB Studio",
        "link_thumb": "https://live.staticflickr.com/65535/51682848768_2e978e6063_o.gif",
        "link_bin": "https://github.com/lmbstudiocontact/mb4_60/raw/main/One Piece Anime_L10_-1110487607_Portuguese.bin",
        "name_language": "Portuguese",
        "id_bin_language": "One Piece Anime_L10_-1110487607_Portuguese"
      },
      {
        "author": "LMB Studio",
        "link_thumb": "https://live.staticflickr.com/65535/51682590501_e21522986f_o.gif",
        "link_bin": "https://github.com/lmbstudiocontact/mb4_60/raw/main/One Piece Anime_L10_-1110487607_Russian.bin",
        "name_language": "Russian",
        "id_bin_language": "One Piece Anime_L10_-1110487607_Russian"
      },
      {
        "author": "LMB Studio",
        "link_thumb": "https://live.staticflickr.com/65535/51683260594_7d776c9c52_o.gif",
        "link_bin": "https://github.com/lmbstudiocontact/mb4_60/raw/main/One Piece Anime_L10_-1110487607_Spanish.bin",
        "name_language": "Spanish",
        "id_bin_language": "One Piece Anime_L10_-1110487607_Spanish"
      }
    ],
    "array_tags": [
      "lmbstudio"
    ],
    "list_album": [
      {
        "id_album": "-1054518188",
        "link_thumb": "https://live.staticflickr.com/65535/51682848338_2e6ae5e56f_o.gif",
        "title": "One Piece Anime_L10"
      }
    ]
  },
  {
    "author": "LMB Studio",
    "link_thumb": "https://live.staticflickr.com/65535/51681795202_143a43e58a_o.gif",
    "link_bin": "https://github.com/lmbstudiocontact/mb4_60/raw/main/One Piece Anime_L10_-1196175591.bin",
    "id_bin": "One Piece Anime_L10_-1196175591",
    "list_language": [
      {
        "author": "LMB Studio",
        "link_thumb": "https://live.staticflickr.com/65535/51683480995_44142c26ef_o.gif",
        "link_bin": "https://github.com/lmbstudiocontact/mb4_60/raw/main/One Piece Anime_L10_-1196175591_English.bin",
        "name_language": "English",
        "id_bin_language": "One Piece Anime_L10_-1196175591_English"
      },
      {
        "author": "LMB Studio",
        "link_thumb": "https://live.staticflickr.com/65535/51682850113_9607c1b7b0_o.gif",
        "link_bin": "https://github.com/lmbstudiocontact/mb4_60/raw/main/One Piece Anime_L10_-1196175591_Portuguese.bin",
        "name_language": "Portuguese",
        "id_bin_language": "One Piece Anime_L10_-1196175591_Portuguese"
      },
      {
        "author": "LMB Studio",
        "link_thumb": "https://live.staticflickr.com/65535/51683481445_2c863c6036_o.gif",
        "link_bin": "https://github.com/lmbstudiocontact/mb4_60/raw/main/One Piece Anime_L10_-1196175591_Russian.bin",
        "name_language": "Russian",
        "id_bin_language": "One Piece Anime_L10_-1196175591_Russian"
      },
      {
        "author": "LMB Studio",
        "link_thumb": "https://live.staticflickr.com/65535/51681796267_450b8dd519_o.gif",
        "link_bin": "https://github.com/lmbstudiocontact/mb4_60/raw/main/One Piece Anime_L10_-1196175591_Spanish.bin",
        "name_language": "Spanish",
        "id_bin_language": "One Piece Anime_L10_-1196175591_Spanish"
      }
    ],
    "array_tags": [
      "lmbstudio"
    ],
    "list_album": [
      {
        "id_album": "-1054518188",
        "link_thumb": "https://live.staticflickr.com/65535/51681795202_143a43e58a_o.gif",
        "title": "One Piece Anime_L10"
      }
    ]
  },
  {
    "author": "LMB Studio",
    "link_thumb": "https://live.staticflickr.com/65535/51681796567_3a55c286fa_o.gif",
    "link_bin": "https://github.com/lmbstudiocontact/mb4_60/raw/main/One Piece Anime_L10_-1271595931.bin",
    "id_bin": "One Piece Anime_L10_-1271595931",
    "list_language": [
      {
        "author": "LMB Studio",
        "link_thumb": "https://live.staticflickr.com/65535/51683482130_7efee72557_o.gif",
        "link_bin": "https://github.com/lmbstudiocontact/mb4_60/raw/main/One Piece Anime_L10_-1271595931_English.bin",
        "name_language": "English",
        "id_bin_language": "One Piece Anime_L10_-1271595931_English"
      },
      {
        "author": "LMB Studio",
        "link_thumb": "https://live.staticflickr.com/65535/51682851593_cd923cb96c_o.gif",
        "link_bin": "https://github.com/lmbstudiocontact/mb4_60/raw/main/One Piece Anime_L10_-1271595931_Portuguese.bin",
        "name_language": "Portuguese",
        "id_bin_language": "One Piece Anime_L10_-1271595931_Portuguese"
      },
      {
        "author": "LMB Studio",
        "link_thumb": "https://live.staticflickr.com/65535/51681797432_48878e9dae_o.gif",
        "link_bin": "https://github.com/lmbstudiocontact/mb4_60/raw/main/One Piece Anime_L10_-1271595931_Russian.bin",
        "name_language": "Russian",
        "id_bin_language": "One Piece Anime_L10_-1271595931_Russian"
      },
      {
        "author": "LMB Studio",
        "link_thumb": "https://live.staticflickr.com/65535/51683263199_5b5aaf2476_o.gif",
        "link_bin": "https://github.com/lmbstudiocontact/mb4_60/raw/main/One Piece Anime_L10_-1271595931_Spanish.bin",
        "name_language": "Spanish",
        "id_bin_language": "One Piece Anime_L10_-1271595931_Spanish"
      }
    ],
    "array_tags": [
      "lmbstudio"
    ],
    "list_album": [
      {
        "id_album": "-1054518188",
        "link_thumb": "https://live.staticflickr.com/65535/51681796567_3a55c286fa_o.gif",
        "title": "One Piece Anime_L10"
      }
    ]
  },
  {
    "author": "LMB Studio",
    "link_thumb": "https://live.staticflickr.com/65535/51681797997_f0f8f29fd2_o.gif",
    "link_bin": "https://github.com/lmbstudiocontact/mb4_60/raw/main/One Piece Anime_L10_-1328232553.bin",
    "id_bin": "One Piece Anime_L10_-1328232553",
    "list_language": [
      {
        "author": "LMB Studio",
        "link_thumb": "https://live.staticflickr.com/65535/51682593761_4b515a94ea_o.gif",
        "link_bin": "https://github.com/lmbstudiocontact/mb4_60/raw/main/One Piece Anime_L10_-1328232553_English.bin",
        "name_language": "English",
        "id_bin_language": "One Piece Anime_L10_-1328232553_English"
      },
      {
        "author": "LMB Studio",
        "link_thumb": "https://live.staticflickr.com/65535/51682593981_9aff01b166_o.gif",
        "link_bin": "https://github.com/lmbstudiocontact/mb4_60/raw/main/One Piece Anime_L10_-1328232553_Portuguese.bin",
        "name_language": "Portuguese",
        "id_bin_language": "One Piece Anime_L10_-1328232553_Portuguese"
      },
      {
        "author": "LMB Studio",
        "link_thumb": "https://live.staticflickr.com/65535/51683483890_98ffdbbf2c_o.gif",
        "link_bin": "https://github.com/lmbstudiocontact/mb4_60/raw/main/One Piece Anime_L10_-1328232553_Russian.bin",
        "name_language": "Russian",
        "id_bin_language": "One Piece Anime_L10_-1328232553_Russian"
      },
      {
        "author": "LMB Studio",
        "link_thumb": "https://live.staticflickr.com/65535/51683484205_a8ca912846_o.gif",
        "link_bin": "https://github.com/lmbstudiocontact/mb4_60/raw/main/One Piece Anime_L10_-1328232553_Spanish.bin",
        "name_language": "Spanish",
        "id_bin_language": "One Piece Anime_L10_-1328232553_Spanish"
      }
    ],
    "array_tags": [
      "lmbstudio"
    ],
    "list_album": [
      {
        "id_album": "-1054518188",
        "link_thumb": "https://live.staticflickr.com/65535/51681797997_f0f8f29fd2_o.gif",
        "title": "One Piece Anime_L10"
      }
    ]
  },
  {
    "author": "LMB Studio",
    "link_thumb": "https://live.staticflickr.com/65535/51682853693_f18bc777ae_o.gif",
    "link_bin": "https://github.com/lmbstudiocontact/mb4_60/raw/main/One Piece Anime_L10_-1328850593.bin",
    "id_bin": "One Piece Anime_L10_-1328850593",
    "list_language": [
      {
        "author": "LMB Studio",
        "link_thumb": "https://live.staticflickr.com/65535/51683265014_aac6509e73_o.gif",
        "link_bin": "https://github.com/lmbstudiocontact/mb4_60/raw/main/One Piece Anime_L10_-1328850593_English.bin",
        "name_language": "English",
        "id_bin_language": "One Piece Anime_L10_-1328850593_English"
      },
      {
        "author": "LMB Studio",
        "link_thumb": "https://live.staticflickr.com/65535/51683265204_2834fe0f84_o.gif",
        "link_bin": "https://github.com/lmbstudiocontact/mb4_60/raw/main/One Piece Anime_L10_-1328850593_Portuguese.bin",
        "name_language": "Portuguese",
        "id_bin_language": "One Piece Anime_L10_-1328850593_Portuguese"
      },
      {
        "author": "LMB Studio",
        "link_thumb": "https://live.staticflickr.com/65535/51682595506_87ef611f59_o.gif",
        "link_bin": "https://github.com/lmbstudiocontact/mb4_60/raw/main/One Piece Anime_L10_-1328850593_Russian.bin",
        "name_language": "Russian",
        "id_bin_language": "One Piece Anime_L10_-1328850593_Russian"
      },
      {
        "author": "LMB Studio",
        "link_thumb": "https://live.staticflickr.com/65535/51683265624_b94e233935_o.gif",
        "link_bin": "https://github.com/lmbstudiocontact/mb4_60/raw/main/One Piece Anime_L10_-1328850593_Spanish.bin",
        "name_language": "Spanish",
        "id_bin_language": "One Piece Anime_L10_-1328850593_Spanish"
      }
    ],
    "array_tags": [
      "lmbstudio"
    ],
    "list_album": [
      {
        "id_album": "-1054518188",
        "link_thumb": "https://live.staticflickr.com/65535/51682853693_f18bc777ae_o.gif",
        "title": "One Piece Anime_L10"
      }
    ]
  },
  {
    "author": "LMB Studio",
    "link_thumb": "https://live.staticflickr.com/65535/51683485740_5914f78f2e_o.gif",
    "link_bin": "https://github.com/lmbstudiocontact/mb4_60/raw/main/One Piece Anime_L10_-1350681719.bin",
    "id_bin": "One Piece Anime_L10_-1350681719",
    "list_language": [
      {
        "author": "LMB Studio",
        "link_thumb": "https://live.staticflickr.com/65535/51682596371_743d19ed15_o.gif",
        "link_bin": "https://github.com/lmbstudiocontact/mb4_60/raw/main/One Piece Anime_L10_-1350681719_English.bin",
        "name_language": "English",
        "id_bin_language": "One Piece Anime_L10_-1350681719_English"
      },
      {
        "author": "LMB Studio",
        "link_thumb": "https://live.staticflickr.com/65535/51681801102_912283f71c_o.gif",
        "link_bin": "https://github.com/lmbstudiocontact/mb4_60/raw/main/One Piece Anime_L10_-1350681719_Portuguese.bin",
        "name_language": "Portuguese",
        "id_bin_language": "One Piece Anime_L10_-1350681719_Portuguese"
      },
      {
        "author": "LMB Studio",
        "link_thumb": "https://live.staticflickr.com/65535/51682596951_2f6b997050_o.gif",
        "link_bin": "https://github.com/lmbstudiocontact/mb4_60/raw/main/One Piece Anime_L10_-1350681719_Russian.bin",
        "name_language": "Russian",
        "id_bin_language": "One Piece Anime_L10_-1350681719_Russian"
      },
      {
        "author": "LMB Studio",
        "link_thumb": "https://live.staticflickr.com/65535/51682597166_b9cf677735_o.gif",
        "link_bin": "https://github.com/lmbstudiocontact/mb4_60/raw/main/One Piece Anime_L10_-1350681719_Spanish.bin",
        "name_language": "Spanish",
        "id_bin_language": "One Piece Anime_L10_-1350681719_Spanish"
      }
    ],
    "array_tags": [
      "lmbstudio"
    ],
    "list_album": [
      {
        "id_album": "-1054518188",
        "link_thumb": "https://live.staticflickr.com/65535/51683485740_5914f78f2e_o.gif",
        "title": "One Piece Anime_L10"
      }
    ]
  },
  {
    "author": "LMB Studio",
    "link_thumb": "https://live.staticflickr.com/65535/51682597511_50204171a5_o.gif",
    "link_bin": "https://github.com/lmbstudiocontact/mb4_60/raw/main/One Piece Anime_L10_-1418593334.bin",
    "id_bin": "One Piece Anime_L10_-1418593334",
    "list_language": [
      {
        "author": "LMB Studio",
        "link_thumb": "https://live.staticflickr.com/65535/51682856578_c3ed428c85_o.gif",
        "link_bin": "https://github.com/lmbstudiocontact/mb4_60/raw/main/One Piece Anime_L10_-1418593334_English.bin",
        "name_language": "English",
        "id_bin_language": "One Piece Anime_L10_-1418593334_English"
      },
      {
        "author": "LMB Studio",
        "link_thumb": "https://live.staticflickr.com/65535/51685132980_bac50672cc_o.gif",
        "link_bin": "https://github.com/lmbstudiocontact/mb4_60/raw/main/One Piece Anime_L10_-1418593334_Portuguese.bin",
        "name_language": "Portuguese",
        "id_bin_language": "One Piece Anime_L10_-1418593334_Portuguese"
      },
      {
        "author": "LMB Studio",
        "link_thumb": "https://live.staticflickr.com/65535/51681802587_7823fa95a6_o.gif",
        "link_bin": "https://github.com/lmbstudiocontact/mb4_60/raw/main/One Piece Anime_L10_-1418593334_Russian.bin",
        "name_language": "Russian",
        "id_bin_language": "One Piece Anime_L10_-1418593334_Russian"
      },
      {
        "author": "LMB Studio",
        "link_thumb": "https://live.staticflickr.com/65535/51682598531_d26c937ba0_o.gif",
        "link_bin": "https://github.com/lmbstudiocontact/mb4_60/raw/main/One Piece Anime_L10_-1418593334_Spanish.bin",
        "name_language": "Spanish",
        "id_bin_language": "One Piece Anime_L10_-1418593334_Spanish"
      }
    ],
    "array_tags": [
      "lmbstudio"
    ],
    "list_album": [
      {
        "id_album": "-1054518188",
        "link_thumb": "https://live.staticflickr.com/65535/51682597511_50204171a5_o.gif",
        "title": "One Piece Anime_L10"
      }
    ]
  },
  {
    "author": "LMB Studio",
    "link_thumb": "https://live.staticflickr.com/65535/51682857718_bf067fd0df_o.gif",
    "link_bin": "https://github.com/lmbstudiocontact/mb4_60/raw/main/One Piece Anime_L10_-1422137764.bin",
    "id_bin": "One Piece Anime_L10_-1422137764",
    "list_language": [
      {
        "author": "LMB Studio",
        "link_thumb": "https://live.staticflickr.com/65535/51681803402_62db12e379_o.gif",
        "link_bin": "https://github.com/lmbstudiocontact/mb4_60/raw/main/One Piece Anime_L10_-1422137764_English.bin",
        "name_language": "English",
        "id_bin_language": "One Piece Anime_L10_-1422137764_English"
      },
      {
        "author": "LMB Studio",
        "link_thumb": "https://live.staticflickr.com/65535/51683489155_c300a34aac_o.gif",
        "link_bin": "https://github.com/lmbstudiocontact/mb4_60/raw/main/One Piece Anime_L10_-1422137764_Portuguese.bin",
        "name_language": "Portuguese",
        "id_bin_language": "One Piece Anime_L10_-1422137764_Portuguese"
      },
      {
        "author": "LMB Studio",
        "link_thumb": "https://live.staticflickr.com/65535/51681803897_e54ccedbcb_o.gif",
        "link_bin": "https://github.com/lmbstudiocontact/mb4_60/raw/main/One Piece Anime_L10_-1422137764_Russian.bin",
        "name_language": "Russian",
        "id_bin_language": "One Piece Anime_L10_-1422137764_Russian"
      },
      {
        "author": "LMB Studio",
        "link_thumb": "https://live.staticflickr.com/65535/51683269654_f3bc0a73fa_o.gif",
        "link_bin": "https://github.com/lmbstudiocontact/mb4_60/raw/main/One Piece Anime_L10_-1422137764_Spanish.bin",
        "name_language": "Spanish",
        "id_bin_language": "One Piece Anime_L10_-1422137764_Spanish"
      }
    ],
    "array_tags": [
      "lmbstudio"
    ],
    "list_album": [
      {
        "id_album": "-1054518188",
        "link_thumb": "https://live.staticflickr.com/65535/51682857718_bf067fd0df_o.gif",
        "title": "One Piece Anime_L10"
      }
    ]
  },
  {
    "author": "LMB Studio",
    "link_thumb": "https://live.staticflickr.com/65535/51683489800_ff51ca5d73_o.gif",
    "link_bin": "https://github.com/lmbstudiocontact/mb4_60/raw/main/One Piece Anime_L10_-1680987875.bin",
    "id_bin": "One Piece Anime_L10_-1680987875",
    "list_language": [
      {
        "author": "LMB Studio",
        "link_thumb": "https://live.staticflickr.com/65535/51683270254_bd90927322_o.gif",
        "link_bin": "https://github.com/lmbstudiocontact/mb4_60/raw/main/One Piece Anime_L10_-1680987875_English.bin",
        "name_language": "English",
        "id_bin_language": "One Piece Anime_L10_-1680987875_English"
      },
      {
        "author": "LMB Studio",
        "link_thumb": "https://live.staticflickr.com/65535/51681804952_66936a4cfd_o.gif",
        "link_bin": "https://github.com/lmbstudiocontact/mb4_60/raw/main/One Piece Anime_L10_-1680987875_Portuguese.bin",
        "name_language": "Portuguese",
        "id_bin_language": "One Piece Anime_L10_-1680987875_Portuguese"
      },
      {
        "author": "LMB Studio",
        "link_thumb": "https://live.staticflickr.com/65535/51683270724_2ac9c66eef_o.gif",
        "link_bin": "https://github.com/lmbstudiocontact/mb4_60/raw/main/One Piece Anime_L10_-1680987875_Russian.bin",
        "name_language": "Russian",
        "id_bin_language": "One Piece Anime_L10_-1680987875_Russian"
      },
      {
        "author": "LMB Studio",
        "link_thumb": "https://live.staticflickr.com/65535/51682859988_46ff417ff5_o.gif",
        "link_bin": "https://github.com/lmbstudiocontact/mb4_60/raw/main/One Piece Anime_L10_-1680987875_Spanish.bin",
        "name_language": "Spanish",
        "id_bin_language": "One Piece Anime_L10_-1680987875_Spanish"
      }
    ],
    "array_tags": [
      "lmbstudio"
    ],
    "list_album": [
      {
        "id_album": "-1054518188",
        "link_thumb": "https://live.staticflickr.com/65535/51683489800_ff51ca5d73_o.gif",
        "title": "One Piece Anime_L10"
      }
    ]
  }
]